<?xml version="1.0" encoding="UTF-8"?>
<metadata><idinfo><citation><citeinfo><origin>U.S. Department of Commerce, U.S. Census Bureau, Geography Division</origin><pubdate>2011</pubdate><title Sync="TRUE">county</title><edition>2011</edition><geoform Sync="TRUE">vector digital data</geoform><onlink>http://www.census.gov/geo/www/tiger</onlink><lworkcit><citeinfo><onlink>http://www.bts.gov/programs/geographic_information_services/</onlink></citeinfo></lworkcit><ftname Sync="TRUE">county</ftname></citeinfo></citation><descript><abstract>County boundaries with shorelines cut in. The TIGER/Line Files are shapefiles and related database files (.dbf) that are an extract of selected geographic and cartographic information from the U.S. Census Bureau's Master Address File / Topologically Integrated Geographic Encoding and Referencing (MAF/TIGER) Database (MTDB).  The MTDB represents a seamless national file with no overlaps or gaps between parts, however, each TIGER/Line File is designed to stand alone as an independent data set, or they can be combined to cover the entire nation.  The primary legal divisions of most States are termed counties.  In Louisiana, these divisions are known as parishes.  In Alaska, which has no counties, the equivalent entities are the organized boroughs, city and boroughs, and municipalities, and for the unorganized area, census areas.  The latter are delineated cooperatively for statistical purposes by the State of Alaska and the Census Bureau.  In four States (Maryland, Missouri, Nevada, and Virginia), there are one or more incorporated places that are independent of any county organization and thus constitute primary divisions of their States.  These incorporated places are known as independent cities and are treated as equivalent entities for purposes of data presentation.  The District of Columbia and Guam have no primary divisions, and each area is considered an equivalent entity for purposes of data presentation.  The Census Bureau treats the following entities as equivalents of counties for purposes of data presentation: Municipios in Puerto Rico, Districts and Islands in American Samoa, Municipalities in the Commonwealth of the Northern Mariana Islands, and Islands in the U.S. Virgin Islands.  The entire area of the United States, Puerto Rico, and the Island Areas is covered by counties or equivalent entities.  The 2010 Census boundaries for counties and equivalent entities are as of January 1, 2010, primarily as reported through the Census Bureau's Boundary and Annexation Survey (BAS).</abstract><purpose>In order for others to use the information in the Census MAF/TIGER database in a geographic information system (GIS) or for other geographic applications, the Census Bureau releases to the public extracts of the database in the form of TIGER/Line Shapefiles.</purpose><langdata Sync="TRUE">en</langdata></descript><timeperd><timeinfo><sngdate><caldate>2012</caldate></sngdate></timeinfo><current>publication date</current></timeperd><status><progress>Complete</progress><update>TIGER/Line Shapefiles are extracted from the Census MAF/TIGER database.  No changes or updates will be made to this version of the TIGER/Line Shapefiles.  Future releases of TIGER/Line Shapefiles will reflect updates made to the Census MAF/TIGER database.</update></status><spdom><bounding><westbc Sync="TRUE">-179.168567</westbc><eastbc Sync="TRUE">179.748709</eastbc><northbc Sync="TRUE">71.389610</northbc><southbc Sync="TRUE">-14.599767</southbc></bounding><lboundng><leftbc Sync="TRUE">-179.168567</leftbc><rightbc Sync="TRUE">179.748709</rightbc><bottombc Sync="TRUE">-14.599767</bottombc><topbc Sync="TRUE">71.389610</topbc></lboundng></spdom><keywords><theme><themekt>ISO 19115 Topic Categories</themekt><themekey>boundaries</themekey><themekey>county</themekey><themekey>polygon</themekey><themekey>line</themekey></theme><theme><themekt>None</themekt><themekey>State or equivalent entity</themekey><themekey>Polygon</themekey></theme><place><placekt>INCITS.38-200x (R2004),INCITS.31-200x (R2007),INCITS.454-200x,INCITS 455-200x,INCITS 446-2008</placekt><placekey>United States of America</placekey><placekey>U.S.</placekey><placekey>U.S.A</placekey></place><stratum><stratkey>gound</stratkey></stratum><temporal><tempkey>2010</tempkey><tempkey>2011</tempkey><tempkey>2012</tempkey></temporal></keywords><accconst>None</accconst><useconst>
The TIGER/Line Shapefile products are not copyrighted however TIGER/Line and Census TIGER are registered trademarks of the U.S. Census Bureau.  These products are free to use in a product or publication, however acknowledgement must be given to the U.S. Census Bureau as the source.
The boundary information in the TIGER/Line Shapefiles are for statistical data collection and tabulation purposes only; their depiction and designation for statistical purposes does not constitute a determination of jurisdictional authority or rights of ownership or entitlement and they are not legal land descriptions.Coordinates in the TIGER/Line shapefiles have six implied decimal places, but the positional accuracy of these coordinates is not as great as the six decimal places suggest.
</useconst><ptcontac><cntinfo><cntorgp><cntorg>Research and Innovative Technology Administration's Bureau of Transportation Statistics (RITA/BTS)</cntorg><cntper>Office of Geospatial Information Systems</cntper></cntorgp><cntaddr><addrtype>mailing and physical address</addrtype><address>1200 New Jersey Ave, SE</address><city>Washington</city><state>DC</state><postal>20590</postal><country>USA</country></cntaddr><cntvoice>202-366-DATA</cntvoice><cntfax>202-366-3640</cntfax><cntemail>answers@bts.gov</cntemail></cntinfo></ptcontac><native Sync="TRUE">Microsoft Windows Vista Version 6.1 (Build 7601) Service Pack 1; ESRI ArcCatalog 9.3.0.1770</native><crossref><citeinfo><onlink>http://www.bts.gov/programs/geographic_information_services/</onlink><lworkcit><citeinfo><onlink>http://www.bts.gov/programs/geographic_information_services/</onlink></citeinfo></lworkcit></citeinfo></crossref><natvform Sync="TRUE">Shapefile</natvform></idinfo><dataqual><attracc><attraccr>Accurate against Federal Information Processing Standards (FIPS), FIPS Publication 6-4, and FIPS-55 at the 100% level for the codes and base names.  The remaining attribute information has been examined but has not been fully tested for accuracy.</attraccr></attracc><logic>
The Census Bureau performed automated tests to ensure logical consistency and limits of shapefiles.  Segments making up the outer and inner boundaries of a polygon tie end-to-end to completely enclose the area.  All polygons are tested for closure.
The Census Bureau uses its internally developed geographic update system to enhance and modify spatial and attribute data in the Census MAF/TIGER database.  Standard geographic codes, such as FIPS codes for states, counties, municipalities, county subdivisions, places, American Indian/Alaska Native/Native Hawaiian areas, and congressional districts are used when encoding spatial entities.  The Census Bureau performed spatial data tests for logical consistency of the codes during the compilation of the original Census MAF/TIGER database files.  Most of the codes for geographic entities except states, counties, urban areas, Core Based Statistical Areas (CBSAs), American Indian Areas (AIAs), and congressional districts were provided to the Census Bureau by the USGS, the agency responsible for maintaining FIPS 55.  Feature attribute information has been examined but has not been fully tested for consistency.
For the TIGER/Line Shapefiles, the Point and Vector Object Count for the G-polygon SDTS Point and Vector Object Type reflects the number of records in the shapefile attribute table.  For multi-polygon features, only one attribute record exists for each multi-polygon rather than one attribute record per individual G-polygon component of the multi-polygon feature.  TIGER/Line Shapefile multi-polygons are an exception to the G-polygon object type classification.  Therefore, when multi-polygons exist in a shapefile, the object count will be less than the actual number of G-polygons.
</logic><complete>Data completeness of the TIGER/Line Shapefiles reflects the contents of the Census MAF/TIGER database at the time the TIGER/Line Shapefiles were created.</complete><lineage><srcinfo><srccite><citeinfo><origin>U.S. Department of Commerce, U.S. Census Bureau, Geography Division</origin><pubdate>Unpublished Material</pubdate><title>Census MAF/TIGER database</title><onlink>http://www.bts.gov/programs/geographic_information_services/</onlink><lworkcit><citeinfo><onlink>http://www.bts.gov/programs/geographic_information_services/</onlink></citeinfo></lworkcit></citeinfo></srccite><typesrc>online</typesrc><srctime><timeinfo><rngdates><begdate>201001</begdate><enddate>201007</enddate></rngdates></timeinfo><srccurr>publication date</srccurr></srctime><srccitea>MAF/TIGER</srccitea><srccontr>The selected geographic and cartographic information (line segments) are derived from the U.S. Census Bureau's Master Address File Topologically Integrated Geographic Encoding and Referencing (MAF/TIGER) database.</srccontr></srcinfo><procstep><procdesc>TIGER/Line Shapefiles are extracted from the Census MAF/TIGER database by nation, state, county, and entity.  Census MAF/TIGER data for all of the aforementioned geographic entities are then distributed among the shapefiles each containing attributes for line, polygon, or landmark geographic data.</procdesc><srcused>Census MAF/TIGER</srcused><procdate>2010</procdate></procstep></lineage></dataqual><spdoinfo><indspref>Federal Information Processing Standards (FIPS), ANSI, and feature names.</indspref><direct Sync="TRUE">Vector</direct><ptvctinf><esriterm><efeatyp Sync="TRUE">Simple</efeatyp><efeageom code="4" Sync="TRUE"></efeageom><esritopo Sync="TRUE">FALSE</esritopo><efeacnt Sync="TRUE">3234</efeacnt><spindex Sync="TRUE">TRUE</spindex><linrefer Sync="TRUE">FALSE</linrefer></esriterm></ptvctinf></spdoinfo><spref><horizsys><geograph><latres Sync="TRUE">0.000000</latres><longres Sync="TRUE">0.000000</longres><geogunit Sync="TRUE">Decimal degrees</geogunit></geograph><geodetic><horizdn Sync="TRUE">D_WGS_1984</horizdn><ellips Sync="TRUE">WGS_1984</ellips><semiaxis Sync="TRUE">6378137.000000</semiaxis><denflat Sync="TRUE">298.257224</denflat></geodetic><cordsysn><geogcsn Sync="TRUE">GCS_WGS_1984</geogcsn></cordsysn></horizsys></spref><eainfo><detailed Name="county"><enttyp><enttypl Sync="TRUE">county</enttypl><enttypd>ESRI shapefile of the United States counties</enttypd><enttypds>ESRI and RITA/BTS</enttypds><enttypt Sync="TRUE">Feature Class</enttypt><enttypc Sync="TRUE">3234</enttypc></enttyp><attr><attrlabl>FID</attrlabl><attrdef>Internal feature number.</attrdef><attrdefs>ESRI</attrdefs><attrdomv><udom>Sequential unique whole numbers that are automatically generated.</udom></attrdomv><attalias Sync="TRUE">FID</attalias><attrtype Sync="TRUE">OID</attrtype><attwidth Sync="TRUE">4</attwidth><atprecis Sync="TRUE">0</atprecis><attscale Sync="TRUE">0</attscale></attr><attr><attrlabl>Shape</attrlabl><attrdef>Feature geometry.</attrdef><attrdefs>ESRI</attrdefs><attrdomv><edom><edomv>"polygon"</edomv><edomvd>A "polygon" is an area feature comprised of points and line segments.</edomvd><edomvds>Assigned</edomvds></edom></attrdomv><attrdomv><udom>Coordinates defining the features.</udom></attrdomv><attalias Sync="TRUE">Shape</attalias><attrtype Sync="TRUE">Geometry</attrtype><attwidth Sync="TRUE">0</attwidth><atprecis Sync="TRUE">0</atprecis><attscale Sync="TRUE">0</attscale></attr><attr><attrlabl>STFIPS</attrlabl><attrdef>State FIPS code</attrdef><attrdefs>Bureau of the Census (BOC)</attrdefs><attrdomv><codesetd><codesetn>Federal Information Processing Standard, Publication 6-4</codesetn><codesets>National Institute for Standards and Technology</codesets></codesetd></attrdomv><attalias Sync="TRUE">STFIPS</attalias><attrtype Sync="TRUE">String</attrtype><attwidth Sync="TRUE">2</attwidth><atprecis Sync="TRUE">0</atprecis><attscale Sync="TRUE">0</attscale></attr><attr><attrlabl>CTFIPS</attrlabl><attrdef>County FIPS code</attrdef><attrdefs>Bureau of the Census (BOC)</attrdefs><attrdomv><codesetd><codesetn>Federal Information Processing Standard, Publication 6-4</codesetn><codesets>National Institute for Standards and Technology</codesets></codesetd></attrdomv><attalias Sync="TRUE">CTFIPS</attalias><attrtype Sync="TRUE">String</attrtype><attwidth Sync="TRUE">5</attwidth><atprecis Sync="TRUE">0</atprecis><attscale Sync="TRUE">0</attscale></attr><attr><attrlabl>STATE</attrlabl><attrdef>State name</attrdef><attrdefs>Bureau of the Census (BOC)</attrdefs><attrdomv><codesetd><codesetn>Offical List of State Names</codesetn><codesets>Bureau of the Census (BOC)</codesets></codesetd></attrdomv><attalias Sync="TRUE">STATE</attalias><attrtype Sync="TRUE">String</attrtype><attwidth Sync="TRUE">66</attwidth><atprecis Sync="TRUE">0</atprecis><attscale Sync="TRUE">0</attscale></attr><attr><attrlabl>COUNTY</attrlabl><attrdef>County name</attrdef><attrdefs>Bureau of the Census (BOC)</attrdefs><attrdomv><codesetd><codesetn>Official List of U.S. County Names</codesetn><codesets>Bureau of the Census (BOC)</codesets></codesetd></attrdomv><attalias Sync="TRUE">COUNTY</attalias><attrtype Sync="TRUE">String</attrtype><attwidth Sync="TRUE">66</attwidth><atprecis Sync="TRUE">0</atprecis><attscale Sync="TRUE">0</attscale></attr><attr><attrlabl>VERSION</attrlabl><attrdef>Version of the database</attrdef><attrdefs>Research and Innovative Technology Administration's Bureau of Transportation Statistics (RITA/BTS)</attrdefs><attrdomv><rdom><rdommin>00</rdommin><rdommax>99</rdommax></rdom></attrdomv><attalias Sync="TRUE">VERSION</attalias><attrtype Sync="TRUE">String</attrtype><attwidth Sync="TRUE">2</attwidth><atprecis Sync="TRUE">0</atprecis><attscale Sync="TRUE">0</attscale></attr></detailed></eainfo><distinfo><distrib><cntinfo><cntorgp><cntorg>Research and Innovative Technology Administration's Bureau of Transportation Statistics (RITA/BTS)</cntorg><cntper>Office of Geospatial Information Systems</cntper></cntorgp><cntaddr><addrtype>mailing address</addrtype><address>1200 New Jersey Avenue, SE</address><city>Washington</city><state>DC</state><postal>20590</postal><country>USA</country></cntaddr><cntvoice>202-366-DATA</cntvoice><cntfax>202-366-3640</cntfax><cntemail>answers@bts.gov</cntemail></cntinfo></distrib><resdesc>National Transportation Atlas Databases (NTAD) 2012</resdesc><distliab>No warranty, expressed or implied is made with regard to the accuracy of these data, and no liability is assumed by the U.S. Government in general or the U.S. Census Bureau in specific as to the spatial or attribute accuracy of the data.  The act of distribution shall not constitute any such warranty and no responsibility is assumed by the U.S. government in the use of these files.  The boundary information in the TIGER/Line Shapefiles is for statistical data collection and tabulation purposes only; their depiction and designation for statistical purposes do not constitute a determination of jurisdictional authority or rights of ownership or entitlement and they are not legal land descriptions.</distliab><stdorder><digform><digtinfo><formname>ESRI Shapefile</formname><formverd>2012</formverd><filedec>PK-ZIP, version 1.93 A or higher</filedec><transize>0.068</transize><dssize Sync="TRUE">161.924</dssize></digtinfo><digtopt><onlinopt><computer><networka><networkr>http://www.census.gov/geo/www/tiger</networkr></networka></computer><accinstr>The NTAD DVD can be ordered from the online bookstore at www.bts.gov.  NTAD can also be downloaded from the Geographic Information Program web sit at http://www.bts.gov/programs/geographic_information_services/.</accinstr></onlinopt><offoptn><offmedia>DVD</offmedia><recfmt>ISO 9660</recfmt></offoptn></digtopt></digform><fees>The online copy of the TIGER/Line files may be accessed without charge.</fees><ordering>Call (202-366-DATA), fax (202-366-3640), or E-mail (answers@bts.gov) RITA/BTS to request the National Transportation Atlas Databases (NTAD) 2012 DVD. The NTAD DVD can be ordered from the online bookstore at www.bts.gov.  Individual datasets from the NTAD can also be downloaded from the Office of Geospatial Information Systems website at http://www.bts.gov/programs/geographic_information_services/.

To obtain more information about ordering TIGER/Line shapefiles visit http://www.census.gov/geo/www/tiger</ordering></stdorder><techpreq>
Software that can process GIS files.

The TIGER/Line shapefiles contain geographic data only and do not include display mapping software or statistical data.  For information on how to use the TIGER/Line shapefile data with specific software package users shall contact the company that produced the software.
</techpreq><availabl><timeinfo><sngdate><caldate>2012</caldate></sngdate></timeinfo></availabl></distinfo><metainfo><metd Sync="TRUE">20120301</metd><metc><cntinfo><cntorgp><cntorg>Research and Innovative Technology Administration's Bureau of Transportation Statisitics (RITA/BTS)</cntorg><cntper>Office of Geospatial Information Systems</cntper></cntorgp><cntaddr><addrtype>mailing address</addrtype><address>1200 New Jersey Ave.</address><city>Washington</city><state>DC</state><postal>20590</postal><country>USA</country></cntaddr><cntvoice>202-366-DATA</cntvoice><cntfax>202-366-3640</cntfax><cntemail>answers@bts.gov</cntemail></cntinfo></metc><metstdn Sync="TRUE">FGDC Content Standards for Digital Geospatial Metadata</metstdn><metstdv Sync="TRUE">FGDC-STD-001-1998</metstdv><mettc Sync="TRUE">local time</mettc><metextns><onlink>http://www.esri.com/metadata/esriprof80.html</onlink><metprof>ESRI Metadata Profile</metprof></metextns><metextns><onlink>http://www.esri.com/metadata/esriprof80.html</onlink><metprof>ESRI Metadata Profile</metprof></metextns><metextns><onlink>http://www.esri.com/metadata/esriprof80.html</onlink><metprof>ESRI Metadata Profile</metprof></metextns><langmeta Sync="TRUE">en</langmeta></metainfo><Esri><CreaDate>20130124</CreaDate><CreaTime>13290400</CreaTime><SyncOnce>FALSE</SyncOnce><SyncDate>20120524</SyncDate><SyncTime>12400200</SyncTime><ModDate>20120524</ModDate><ModTime>12400200</ModTime><DataProperties><itemProps><itemName Sync="TRUE">county</itemName><nativeExtBox><westBL Sync="TRUE">-179.168567</westBL><eastBL Sync="TRUE">179.748709</eastBL><southBL Sync="TRUE">-14.599767</southBL><northBL Sync="TRUE">71.389610</northBL><exTypeCode Sync="TRUE">1</exTypeCode></nativeExtBox><itemSize Sync="TRUE">161.924</itemSize><itemLocation><linkage Sync="FALSE">withheld</linkage><protocol Sync="TRUE">Local Area Network</protocol></itemLocation><imsContentType Sync="TRUE">002</imsContentType></itemProps><coordRef><type Sync="TRUE">Geographic</type><geogcsn Sync="TRUE">GCS_WGS_1984</geogcsn><csUnits Sync="TRUE">Angular Unit: Degree (0.017453)</csUnits><peXml Sync="TRUE">&lt;GeographicCoordinateSystem xsi:type='typens:GeographicCoordinateSystem' xmlns:xsi='http://www.w3.org/2001/XMLSchema-instance' xmlns:xs='http://www.w3.org/2001/XMLSchema' xmlns:typens='http://www.esri.com/schemas/ArcGIS/10.0'&gt;&lt;WKT&gt;GEOGCS[&amp;quot;GCS_WGS_1984&amp;quot;,DATUM[&amp;quot;D_WGS_1984&amp;quot;,SPHEROID[&amp;quot;WGS_1984&amp;quot;,6378137.0,298.257223563]],PRIMEM[&amp;quot;Greenwich&amp;quot;,0.0],UNIT[&amp;quot;Degree&amp;quot;,0.0174532925199433],AUTHORITY[&amp;quot;EPSG&amp;quot;,4326]]&lt;/WKT&gt;&lt;XOrigin&gt;-399.99999999999989&lt;/XOrigin&gt;&lt;YOrigin&gt;-399.99999999999989&lt;/YOrigin&gt;&lt;XYScale&gt;11258999068426.24&lt;/XYScale&gt;&lt;ZOrigin&gt;-100000&lt;/ZOrigin&gt;&lt;ZScale&gt;10000&lt;/ZScale&gt;&lt;MOrigin&gt;-100000&lt;/MOrigin&gt;&lt;MScale&gt;10000&lt;/MScale&gt;&lt;XYTolerance&gt;8.9831528411952133e-009&lt;/XYTolerance&gt;&lt;ZTolerance&gt;0.001&lt;/ZTolerance&gt;&lt;MTolerance&gt;0.001&lt;/MTolerance&gt;&lt;HighPrecision&gt;true&lt;/HighPrecision&gt;&lt;LeftLongitude&gt;-180&lt;/LeftLongitude&gt;&lt;WKID&gt;4326&lt;/WKID&gt;&lt;/GeographicCoordinateSystem&gt;</peXml></coordRef><lineage><Process ToolSource="c:\program files (x86)\arcgis\desktop10.0\ArcToolbox\Toolboxes\Data Management Tools.tbx\Project" Date="20121119" Time="115558">Project coastalCoUTM17 D:\Temp\GCAMP\NTAD2012\utm\coastalCoUTM17.shp PROJCS['NAD_1983_UTM_Zone_17N',GEOGCS['GCS_North_American_1983',DATUM['D_North_American_1983',SPHEROID['GRS_1980',6378137.0,298.257222101]],PRIMEM['Greenwich',0.0],UNIT['Degree',0.0174532925199433]],PROJECTION['Transverse_Mercator'],PARAMETER['False_Easting',500000.0],PARAMETER['False_Northing',0.0],PARAMETER['Central_Meridian',-81.0],PARAMETER['Scale_Factor',0.9996],PARAMETER['Latitude_Of_Origin',0.0],UNIT['Meter',1.0]] WGS_1984_(ITRF00)_To_NAD_1983 GEOGCS['GCS_WGS_1984',DATUM['D_WGS_1984',SPHEROID['WGS_1984',6378137.0,298.257223563]],PRIMEM['Greenwich',0.0],UNIT['Degree',0.0174532925199433]]</Process><Process ToolSource="c:\program files (x86)\arcgis\desktop10.0\ArcToolbox\Toolboxes\Data Management Tools.tbx\Project" Date="20130122" Time="145443">Project Administrative\CoastalCounties C:\GISDATA\GACMSP\GCAMP\WGS84\NTAD\CoastalCounties.shp PROJCS['World_Mercator',GEOGCS['GCS_WGS_1984',DATUM['D_WGS_1984',SPHEROID['WGS_1984',6378137.0,298.257223563]],PRIMEM['Greenwich',0.0],UNIT['Degree',0.0174532925199433]],PROJECTION['Mercator'],PARAMETER['False_Easting',0.0],PARAMETER['False_Northing',0.0],PARAMETER['Central_Meridian',0.0],PARAMETER['Standard_Parallel_1',0.0],UNIT['Meter',1.0]] NAD_1983_To_WGS_1984_1 PROJCS['NAD_1983_UTM_Zone_17N',GEOGCS['GCS_North_American_1983',DATUM['D_North_American_1983',SPHEROID['GRS_1980',6378137.0,298.257222101]],PRIMEM['Greenwich',0.0],UNIT['Degree',0.0174532925199433]],PROJECTION['Transverse_Mercator'],PARAMETER['False_Easting',500000.0],PARAMETER['False_Northing',0.0],PARAMETER['Central_Meridian',-81.0],PARAMETER['Scale_Factor',0.9996],PARAMETER['Latitude_Of_Origin',0.0],UNIT['Meter',1.0]]</Process><Process ToolSource="c:\program files (x86)\arcgis\desktop10.0\ArcToolbox\Toolboxes\Data Management Tools.tbx\Project" Date="20130124" Time="132904">Project Administrative\CoastalCounties C:\GISDATA\GACMSP\GCAMP\WM84\NTAD\CoastalCounties.shp PROJCS['WGS_1984_Web_Mercator_Auxiliary_Sphere',GEOGCS['GCS_WGS_1984',DATUM['D_WGS_1984',SPHEROID['WGS_1984',6378137.0,298.257223563]],PRIMEM['Greenwich',0.0],UNIT['Degree',0.0174532925199433]],PROJECTION['Mercator_Auxiliary_Sphere'],PARAMETER['False_Easting',0.0],PARAMETER['False_Northing',0.0],PARAMETER['Central_Meridian',0.0],PARAMETER['Standard_Parallel_1',0.0],PARAMETER['Auxiliary_Sphere_Type',0.0],UNIT['Meter',1.0]] # PROJCS['World_Mercator',GEOGCS['GCS_WGS_1984',DATUM['D_WGS_1984',SPHEROID['WGS_1984',6378137.0,298.257223563]],PRIMEM['Greenwich',0.0],UNIT['Degree',0.0174532925199433]],PROJECTION['Mercator'],PARAMETER['False_Easting',0.0],PARAMETER['False_Northing',0.0],PARAMETER['Central_Meridian',0.0],PARAMETER['Standard_Parallel_1',0.0],UNIT['Meter',1.0]]</Process></lineage></DataProperties><ArcGISFormat>1.0</ArcGISFormat><ArcGISProfile>ISO19139</ArcGISProfile></Esri><mdLang><languageCode value="eng"/><countryCode value="USA" Sync="TRUE"/></mdLang><mdHrLv><ScopeCd value="005"/></mdHrLv><mdContact><rpIndName>Office of Geospatial Information Systems</rpIndName><rpOrgName>Research and Innovative Technology Administration's Bureau of Transportation Statisitics (RITA/BTS)</rpOrgName><rpCntInfo><cntPhone><voiceNum>202-366-DATA</voiceNum><faxNum>202-366-3640</faxNum></cntPhone><cntAddress addressType="postal"><delPoint>1200 New Jersey Ave.</delPoint><city>Washington</city><adminArea>DC</adminArea><postCode>20590</postCode><country>US</country><eMailAdd>answers@bts.gov</eMailAdd></cntAddress></rpCntInfo><role><RoleCd value="007"/></role></mdContact><mdStanName>ArcGIS Metadata</mdStanName><mdStanVer>1.0</mdStanVer><distInfo><distributor><distorCont><rpIndName>Office of Geospatial Information Systems</rpIndName><rpOrgName>Research and Innovative Technology Administration's Bureau of Transportation Statistics (RITA/BTS)</rpOrgName><rpCntInfo><cntPhone><voiceNum>202-366-DATA</voiceNum><faxNum>202-366-3640</faxNum></cntPhone><cntAddress addressType="postal"><delPoint>1200 New Jersey Avenue, SE</delPoint><city>Washington</city><adminArea>DC</adminArea><postCode>20590</postCode><country>US</country><eMailAdd>answers@bts.gov</eMailAdd></cntAddress></rpCntInfo><role><RoleCd value="005"/></role></distorCont><distorOrdPrc><resFees>The online copy of the TIGER/Line files may be accessed without charge.</resFees><planAvDtTm>2012-01-01</planAvDtTm><ordInstr>Call (202-366-DATA), fax (202-366-3640), or E-mail (answers@bts.gov) RITA/BTS to request the National Transportation Atlas Databases (NTAD) 2012 DVD. The NTAD DVD can be ordered from the online bookstore at www.bts.gov. Individual datasets from the NTAD can also be downloaded from the Office of Geospatial Information Systems website at http://www.bts.gov/programs/geographic_information_services/. To obtain more information about ordering TIGER/Line shapefiles visit http://www.census.gov/geo/www/tiger</ordInstr></distorOrdPrc><distorFormat><formatName>ESRI Shapefile</formatName><formatVer>20120101</formatVer><fileDecmTech>PK-ZIP, version 1.93 A or higher</fileDecmTech></distorFormat><distorTran><transSize>0.068</transSize><onLineSrc><linkage>http://www.census.gov/geo/www/tiger</linkage></onLineSrc></distorTran><distorTran><transSize>0.068</transSize><offLineMed><medName><MedNameCd value="002"/></medName><medFormat><MedFormCd value="004"/></medFormat></offLineMed></distorTran><distorTran><onLineSrc><orDesc>National Transportation Atlas Databases (NTAD) 2012</orDesc></onLineSrc></distorTran></distributor><distTranOps><onLineSrc><linkage>http://www.census.gov/geo/www/tiger</linkage></onLineSrc><transSize Sync="TRUE">161.924</transSize></distTranOps><distFormat><formatName Sync="TRUE">Shapefile</formatName></distFormat></distInfo><dataIdInfo><idCitation><date><pubDate>2011-01-01T00:00:00</pubDate></date><resEd>2012</resEd><citRespParty><rpOrgName>U.S. Department of Commerce, U.S. Census Bureau, Geography Division</rpOrgName><role><RoleCd value="006"/></role></citRespParty><citOnlineRes><linkage>http://www.census.gov/geo/www/tiger</linkage></citOnlineRes><resTitle Sync="TRUE">county</resTitle><presForm><PresFormCd value="005" Sync="TRUE"/></presForm></idCitation><idAbs>&lt;DIV STYLE="text-align:Left;"&gt;&lt;DIV&gt;&lt;DIV&gt;&lt;P&gt;&lt;SPAN&gt;County boundaries with shorelines cut in. The TIGER/Line Files are shapefiles and related database files (.dbf) that are an extract of selected geographic and cartographic information from the U.S. Census Bureau's Master Address File / Topologically Integrated Geographic Encoding and Referencing (MAF/TIGER) Database (MTDB). The MTDB represents a seamless national file with no overlaps or gaps between parts, however, each TIGER/Line File is designed to stand alone as an independent data set, or they can be combined to cover the entire nation. The primary legal divisions of most States are termed counties. In Louisiana, these divisions are known as parishes. In Alaska, which has no counties, the equivalent entities are the organized boroughs, city and boroughs, and municipalities, and for the unorganized area, census areas. The latter are delineated cooperatively for statistical purposes by the State of Alaska and the Census Bureau. In four States (Maryland, Missouri, Nevada, and Virginia), there are one or more incorporated places that are independent of any county organization and thus constitute primary divisions of their States. These incorporated places are known as independent cities and are treated as equivalent entities for purposes of data presentation. The District of Columbia and Guam have no primary divisions, and each area is considered an equivalent entity for purposes of data presentation. The Census Bureau treats the following entities as equivalents of counties for purposes of data presentation: Municipios in Puerto Rico, Districts and Islands in American Samoa, Municipalities in the Commonwealth of the Northern Mariana Islands, and Islands in the U.S. Virgin Islands. The entire area of the United States, Puerto Rico, and the Island Areas is covered by counties or equivalent entities. The 2010 Census boundaries for counties and equivalent entities are as of January 1, 2010, primarily as reported through the Census Bureau's Boundary and Annexation Survey (BAS).&lt;/SPAN&gt;&lt;/P&gt;&lt;/DIV&gt;&lt;/DIV&gt;&lt;/DIV&gt;</idAbs><idPurp>In order for others to use the information in the Census MAF/TIGER database in a geographic information system (GIS) or for other geographic applications, the Census Bureau releases to the public extracts of the database in the form of TIGER/Line Shapefiles.</idPurp><idStatus><ProgCd value="001"/></idStatus><idPoC><rpIndName>Office of Geospatial Information Systems</rpIndName><rpOrgName>Research and Innovative Technology Administration's Bureau of Transportation Statistics (RITA/BTS)</rpOrgName><rpCntInfo><cntPhone><voiceNum>202-366-DATA</voiceNum><faxNum>202-366-3640</faxNum></cntPhone><cntAddress addressType="both"><delPoint>1200 New Jersey Ave, SE</delPoint><city>Washington</city><adminArea>DC</adminArea><postCode>20590</postCode><country>US</country><eMailAdd>answers@bts.gov</eMailAdd></cntAddress></rpCntInfo><role><RoleCd value="007"/></role></idPoC><placeKeys><thesaName><resTitle>INCITS.38-200x (R2004),INCITS.31-200x (R2007),INCITS.454-200x,INCITS 455-200x,INCITS 446-2008</resTitle></thesaName><keyword>U.S.A</keyword><keyword>United States of America</keyword><keyword>U.S.</keyword></placeKeys><stratKeys><keyword>gound</keyword></stratKeys><tempKeys><keyword>2011</keyword><keyword>2010</keyword><keyword>2012</keyword></tempKeys><themeKeys><thesaName><resTitle>ISO 19115 Topic Categories</resTitle></thesaName><keyword>line</keyword><keyword>boundaries</keyword><keyword>county</keyword><keyword>polygon</keyword></themeKeys><themeKeys><keyword>Polygon</keyword><keyword>State or equivalent entity</keyword></themeKeys><searchKeys><keyword>line</keyword><keyword>U.S.A</keyword><keyword>boundaries</keyword><keyword>county</keyword><keyword>polygon</keyword><keyword>gound</keyword><keyword>Polygon</keyword><keyword>2011</keyword><keyword>2010</keyword><keyword>2012</keyword><keyword>State or equivalent entity</keyword><keyword>United States of America</keyword><keyword>U.S.</keyword></searchKeys><resConst><LegConsts><useLimit>No warranty, expressed or implied is made with regard to the accuracy of these data, and no liability is assumed by the U.S. Government in general or the U.S. Census Bureau in specific as to the spatial or attribute accuracy of the data. The act of distribution shall not constitute any such warranty and no responsibility is assumed by the U.S. government in the use of these files. The boundary information in the TIGER/Line Shapefiles is for statistical data collection and tabulation purposes only; their depiction and designation for statistical purposes do not constitute a determination of jurisdictional authority or rights of ownership or entitlement and they are not legal land descriptions.</useLimit></LegConsts></resConst><resConst><Consts><useLimit>The TIGER/Line Shapefile products are not copyrighted however TIGER/Line and Census TIGER are registered trademarks of the U.S. Census Bureau. These products are free to use in a product or publication, however acknowledgement must be given to the U.S. Census Bureau as the source. The boundary information in the TIGER/Line Shapefiles are for statistical data collection and tabulation purposes only; their depiction and designation for statistical purposes does not constitute a determination of jurisdictional authority or rights of ownership or entitlement and they are not legal land descriptions.Coordinates in the TIGER/Line shapefiles have six implied decimal places, but the positional accuracy of these coordinates is not as great as the six decimal places suggest.</useLimit></Consts></resConst><aggrInfo><aggrDSName><citOnlineRes><linkage>http://www.bts.gov/programs/geographic_information_services/</linkage></citOnlineRes></aggrDSName><assocType><AscTypeCd value="001"/></assocType></aggrInfo><aggrInfo><aggrDSName><citOnlineRes><linkage>http://www.bts.gov/programs/geographic_information_services/</linkage></citOnlineRes></aggrDSName><assocType><AscTypeCd value="002"/></assocType></aggrInfo><dataLang><languageCode value="eng"/><countryCode value="USA" Sync="TRUE"/></dataLang><dataExt><exDesc>publication date</exDesc><tempEle><TempExtent><exTemp><TM_Instant><tmPosition>2012-01-01</tmPosition></TM_Instant></exTemp></TempExtent></tempEle></dataExt><envirDesc Sync="TRUE">Microsoft Windows 7 Version 6.1 (Build 7601) Service Pack 1; ESRI ArcGIS 10.0.3.3600</envirDesc><spatRpType><SpatRepTypCd value="001" Sync="TRUE"/></spatRpType><dataExt><geoEle><GeoBndBox esriExtentType="search"><exTypeCode Sync="TRUE">1</exTypeCode><westBL Sync="TRUE">-179.168567</westBL><eastBL Sync="TRUE">179.748709</eastBL><northBL Sync="TRUE">71.389610</northBL><southBL Sync="TRUE">-14.599767</southBL></GeoBndBox></geoEle></dataExt><tpCat><TopicCatCd value="003"/></tpCat></dataIdInfo><dqInfo><dqScope><scpLvl><ScopeCd value="005"/></scpLvl></dqScope><report type="DQConcConsis"><measDesc>The Census Bureau performed automated tests to ensure logical consistency and limits of shapefiles. Segments making up the outer and inner boundaries of a polygon tie end-to-end to completely enclose the area. All polygons are tested for closure. The Census Bureau uses its internally developed geographic update system to enhance and modify spatial and attribute data in the Census MAF/TIGER database. Standard geographic codes, such as FIPS codes for states, counties, municipalities, county subdivisions, places, American Indian/Alaska Native/Native Hawaiian areas, and congressional districts are used when encoding spatial entities. The Census Bureau performed spatial data tests for logical consistency of the codes during the compilation of the original Census MAF/TIGER database files. Most of the codes for geographic entities except states, counties, urban areas, Core Based Statistical Areas (CBSAs), American Indian Areas (AIAs), and congressional districts were provided to the Census Bureau by the USGS, the agency responsible for maintaining FIPS 55. Feature attribute information has been examined but has not been fully tested for consistency. For the TIGER/Line Shapefiles, the Point and Vector Object Count for the G-polygon SDTS Point and Vector Object Type reflects the number of records in the shapefile attribute table. For multi-polygon features, only one attribute record exists for each multi-polygon rather than one attribute record per individual G-polygon component of the multi-polygon feature. TIGER/Line Shapefile multi-polygons are an exception to the G-polygon object type classification. Therefore, when multi-polygons exist in a shapefile, the object count will be less than the actual number of G-polygons.</measDesc></report><report type="DQCompOm"><measDesc>Data completeness of the TIGER/Line Shapefiles reflects the contents of the Census MAF/TIGER database at the time the TIGER/Line Shapefiles were created.</measDesc></report><report type="DQQuanAttAcc"><measDesc>Accurate against Federal Information Processing Standards (FIPS), FIPS Publication 6-4, and FIPS-55 at the 100% level for the codes and base names. The remaining attribute information has been examined but has not been fully tested for accuracy.</measDesc></report><dataLineage><prcStep><stepDesc>TIGER/Line Shapefiles are extracted from the Census MAF/TIGER database by nation, state, county, and entity. Census MAF/TIGER data for all of the aforementioned geographic entities are then distributed among the shapefiles each containing attributes for line, polygon, or landmark geographic data.</stepDesc><stepDateTm>2010-01-01</stepDateTm><stepSrc type="used"><srcCitatn><resAltTitle>Census MAF/TIGER</resAltTitle></srcCitatn></stepSrc></prcStep><dataSource><srcDesc>The selected geographic and cartographic information (line segments) are derived from the U.S. Census Bureau's Master Address File Topologically Integrated Geographic Encoding and Referencing (MAF/TIGER) database.</srcDesc><srcMedName><MedNameCd value="015"/></srcMedName><srcCitatn><resTitle>Census MAF/TIGER database</resTitle><resAltTitle>MAF/TIGER</resAltTitle><date><pubDate date="inapplicable"/></date><citRespParty><rpOrgName>U.S. Department of Commerce, U.S. Census Bureau, Geography Division</rpOrgName><role><RoleCd value="006"/></role></citRespParty><citOnlineRes><linkage>http://www.bts.gov/programs/geographic_information_services/</linkage></citOnlineRes></srcCitatn><srcExt><exDesc>publication date</exDesc><tempEle><TempExtent><exTemp><TM_Period><tmBegin>2010-01-01</tmBegin><tmEnd>2010-07-01</tmEnd></TM_Period></exTemp></TempExtent></tempEle></srcExt></dataSource></dataLineage></dqInfo><spatRepInfo><Indref>Federal Information Processing Standards (FIPS), ANSI, and feature names.</Indref><VectSpatRep><geometObjs Name="county"><geoObjTyp><GeoObjTypCd value="002" Sync="TRUE"></GeoObjTypCd></geoObjTyp><geoObjCnt Sync="TRUE">3234</geoObjCnt></geometObjs><topLvl><TopoLevCd value="001" Sync="TRUE"></TopoLevCd></topLvl></VectSpatRep></spatRepInfo><Binary><Enclosure><Descript>original metadata</Descript><Data SourceMetadata="yes" OriginalFileName="source_metadata.xml" SourceMetadataDigest="da5ee2e4fbeb7c6d0b80f7ed67aaa5" EsriPropertyType="Base64" SourceMetadataSchema="fgdc">PD94bWwgdmVyc2lvbj0iMS4wIiBlbmNvZGluZz0idXRmLTgiPz4NCjxtZXRhZGF0YT4NCiAgPGlk
aW5mbz4NCiAgICA8Y2l0YXRpb24+DQogICAgICA8Y2l0ZWluZm8+DQogICAgICAgIDxvcmlnaW4+
VS5TLiBEZXBhcnRtZW50IG9mIENvbW1lcmNlLCBVLlMuIENlbnN1cyBCdXJlYXUsIEdlb2dyYXBo
eSBEaXZpc2lvbjwvb3JpZ2luPg0KICAgICAgICA8cHViZGF0ZT4yMDExPC9wdWJkYXRlPg0KICAg
ICAgICA8ZWRpdGlvbj4yMDExPC9lZGl0aW9uPg0KICAgICAgICA8b25saW5rPmh0dHA6Ly93d3cu
Y2Vuc3VzLmdvdi9nZW8vd3d3L3RpZ2VyPC9vbmxpbms+DQogICAgICAgIDxsd29ya2NpdD4NCiAg
ICAgICAgICA8Y2l0ZWluZm8+DQogICAgICAgICAgICA8b25saW5rPmh0dHA6Ly93d3cuYnRzLmdv
di9wcm9ncmFtcy9nZW9ncmFwaGljX2luZm9ybWF0aW9uX3NlcnZpY2VzLzwvb25saW5rPg0KICAg
ICAgICAgIDwvY2l0ZWluZm8+DQogICAgICAgIDwvbHdvcmtjaXQ+DQogICAgICA8L2NpdGVpbmZv
Pg0KICAgIDwvY2l0YXRpb24+DQogICAgPGRlc2NyaXB0Pg0KICAgICAgPGFic3RyYWN0PkNvdW50
eSBib3VuZGFyaWVzIHdpdGggc2hvcmVsaW5lcyBjdXQgaW4uIFRoZSBUSUdFUi9MaW5lIEZpbGVz
IGFyZSBzaGFwZWZpbGVzIGFuZCByZWxhdGVkIGRhdGFiYXNlIGZpbGVzICguZGJmKSB0aGF0IGFy
ZSBhbiBleHRyYWN0IG9mIHNlbGVjdGVkIGdlb2dyYXBoaWMgYW5kIGNhcnRvZ3JhcGhpYyBpbmZv
cm1hdGlvbiBmcm9tIHRoZSBVLlMuIENlbnN1cyBCdXJlYXUncyBNYXN0ZXIgQWRkcmVzcyBGaWxl
IC8gVG9wb2xvZ2ljYWxseSBJbnRlZ3JhdGVkIEdlb2dyYXBoaWMgRW5jb2RpbmcgYW5kIFJlZmVy
ZW5jaW5nIChNQUYvVElHRVIpIERhdGFiYXNlIChNVERCKS4gIFRoZSBNVERCIHJlcHJlc2VudHMg
YSBzZWFtbGVzcyBuYXRpb25hbCBmaWxlIHdpdGggbm8gb3ZlcmxhcHMgb3IgZ2FwcyBiZXR3ZWVu
IHBhcnRzLCBob3dldmVyLCBlYWNoIFRJR0VSL0xpbmUgRmlsZSBpcyBkZXNpZ25lZCB0byBzdGFu
ZCBhbG9uZSBhcyBhbiBpbmRlcGVuZGVudCBkYXRhIHNldCwgb3IgdGhleSBjYW4gYmUgY29tYmlu
ZWQgdG8gY292ZXIgdGhlIGVudGlyZSBuYXRpb24uICBUaGUgcHJpbWFyeSBsZWdhbCBkaXZpc2lv
bnMgb2YgbW9zdCBTdGF0ZXMgYXJlIHRlcm1lZCBjb3VudGllcy4gIEluIExvdWlzaWFuYSwgdGhl
c2UgZGl2aXNpb25zIGFyZSBrbm93biBhcyBwYXJpc2hlcy4gIEluIEFsYXNrYSwgd2hpY2ggaGFz
IG5vIGNvdW50aWVzLCB0aGUgZXF1aXZhbGVudCBlbnRpdGllcyBhcmUgdGhlIG9yZ2FuaXplZCBi
b3JvdWdocywgY2l0eSBhbmQgYm9yb3VnaHMsIGFuZCBtdW5pY2lwYWxpdGllcywgYW5kIGZvciB0
aGUgdW5vcmdhbml6ZWQgYXJlYSwgY2Vuc3VzIGFyZWFzLiAgVGhlIGxhdHRlciBhcmUgZGVsaW5l
YXRlZCBjb29wZXJhdGl2ZWx5IGZvciBzdGF0aXN0aWNhbCBwdXJwb3NlcyBieSB0aGUgU3RhdGUg
b2YgQWxhc2thIGFuZCB0aGUgQ2Vuc3VzIEJ1cmVhdS4gIEluIGZvdXIgU3RhdGVzIChNYXJ5bGFu
ZCwgTWlzc291cmksIE5ldmFkYSwgYW5kIFZpcmdpbmlhKSwgdGhlcmUgYXJlIG9uZSBvciBtb3Jl
IGluY29ycG9yYXRlZCBwbGFjZXMgdGhhdCBhcmUgaW5kZXBlbmRlbnQgb2YgYW55IGNvdW50eSBv
cmdhbml6YXRpb24gYW5kIHRodXMgY29uc3RpdHV0ZSBwcmltYXJ5IGRpdmlzaW9ucyBvZiB0aGVp
ciBTdGF0ZXMuICBUaGVzZSBpbmNvcnBvcmF0ZWQgcGxhY2VzIGFyZSBrbm93biBhcyBpbmRlcGVu
ZGVudCBjaXRpZXMgYW5kIGFyZSB0cmVhdGVkIGFzIGVxdWl2YWxlbnQgZW50aXRpZXMgZm9yIHB1
cnBvc2VzIG9mIGRhdGEgcHJlc2VudGF0aW9uLiAgVGhlIERpc3RyaWN0IG9mIENvbHVtYmlhIGFu
ZCBHdWFtIGhhdmUgbm8gcHJpbWFyeSBkaXZpc2lvbnMsIGFuZCBlYWNoIGFyZWEgaXMgY29uc2lk
ZXJlZCBhbiBlcXVpdmFsZW50IGVudGl0eSBmb3IgcHVycG9zZXMgb2YgZGF0YSBwcmVzZW50YXRp
b24uICBUaGUgQ2Vuc3VzIEJ1cmVhdSB0cmVhdHMgdGhlIGZvbGxvd2luZyBlbnRpdGllcyBhcyBl
cXVpdmFsZW50cyBvZiBjb3VudGllcyBmb3IgcHVycG9zZXMgb2YgZGF0YSBwcmVzZW50YXRpb246
IE11bmljaXBpb3MgaW4gUHVlcnRvIFJpY28sIERpc3RyaWN0cyBhbmQgSXNsYW5kcyBpbiBBbWVy
aWNhbiBTYW1vYSwgTXVuaWNpcGFsaXRpZXMgaW4gdGhlIENvbW1vbndlYWx0aCBvZiB0aGUgTm9y
dGhlcm4gTWFyaWFuYSBJc2xhbmRzLCBhbmQgSXNsYW5kcyBpbiB0aGUgVS5TLiBWaXJnaW4gSXNs
YW5kcy4gIFRoZSBlbnRpcmUgYXJlYSBvZiB0aGUgVW5pdGVkIFN0YXRlcywgUHVlcnRvIFJpY28s
IGFuZCB0aGUgSXNsYW5kIEFyZWFzIGlzIGNvdmVyZWQgYnkgY291bnRpZXMgb3IgZXF1aXZhbGVu
dCBlbnRpdGllcy4gIFRoZSAyMDEwIENlbnN1cyBib3VuZGFyaWVzIGZvciBjb3VudGllcyBhbmQg
ZXF1aXZhbGVudCBlbnRpdGllcyBhcmUgYXMgb2YgSmFudWFyeSAxLCAyMDEwLCBwcmltYXJpbHkg
YXMgcmVwb3J0ZWQgdGhyb3VnaCB0aGUgQ2Vuc3VzIEJ1cmVhdSdzIEJvdW5kYXJ5IGFuZCBBbm5l
eGF0aW9uIFN1cnZleSAoQkFTKS48L2Fic3RyYWN0Pg0KICAgICAgPHB1cnBvc2U+SW4gb3JkZXIg
Zm9yIG90aGVycyB0byB1c2UgdGhlIGluZm9ybWF0aW9uIGluIHRoZSBDZW5zdXMgTUFGL1RJR0VS
IGRhdGFiYXNlIGluIGEgZ2VvZ3JhcGhpYyBpbmZvcm1hdGlvbiBzeXN0ZW0gKEdJUykgb3IgZm9y
IG90aGVyIGdlb2dyYXBoaWMgYXBwbGljYXRpb25zLCB0aGUgQ2Vuc3VzIEJ1cmVhdSByZWxlYXNl
cyB0byB0aGUgcHVibGljIGV4dHJhY3RzIG9mIHRoZSBkYXRhYmFzZSBpbiB0aGUgZm9ybSBvZiBU
SUdFUi9MaW5lIFNoYXBlZmlsZXMuPC9wdXJwb3NlPg0KICAgIDwvZGVzY3JpcHQ+DQogICAgPHRp
bWVwZXJkPg0KICAgICAgPHRpbWVpbmZvPg0KICAgICAgICA8c25nZGF0ZT4NCiAgICAgICAgICA8
Y2FsZGF0ZT4yMDEyPC9jYWxkYXRlPg0KICAgICAgICA8L3NuZ2RhdGU+DQogICAgICA8L3RpbWVp
bmZvPg0KICAgICAgPGN1cnJlbnQ+cHVibGljYXRpb24gZGF0ZTwvY3VycmVudD4NCiAgICA8L3Rp
bWVwZXJkPg0KICAgIDxzdGF0dXM+DQogICAgICA8cHJvZ3Jlc3M+Q29tcGxldGU8L3Byb2dyZXNz
Pg0KICAgICAgPHVwZGF0ZT5USUdFUi9MaW5lIFNoYXBlZmlsZXMgYXJlIGV4dHJhY3RlZCBmcm9t
IHRoZSBDZW5zdXMgTUFGL1RJR0VSIGRhdGFiYXNlLiAgTm8gY2hhbmdlcyBvciB1cGRhdGVzIHdp
bGwgYmUgbWFkZSB0byB0aGlzIHZlcnNpb24gb2YgdGhlIFRJR0VSL0xpbmUgU2hhcGVmaWxlcy4g
IEZ1dHVyZSByZWxlYXNlcyBvZiBUSUdFUi9MaW5lIFNoYXBlZmlsZXMgd2lsbCByZWZsZWN0IHVw
ZGF0ZXMgbWFkZSB0byB0aGUgQ2Vuc3VzIE1BRi9USUdFUiBkYXRhYmFzZS48L3VwZGF0ZT4NCiAg
ICA8L3N0YXR1cz4NCiAgICA8a2V5d29yZHM+DQogICAgICA8dGhlbWU+DQogICAgICAgIDx0aGVt
ZWt0PklTTyAxOTExNSBUb3BpYyBDYXRlZ29yaWVzPC90aGVtZWt0Pg0KICAgICAgICA8dGhlbWVr
ZXk+Ym91bmRhcmllczwvdGhlbWVrZXk+DQogICAgICAgIDx0aGVtZWtleT5jb3VudHk8L3RoZW1l
a2V5Pg0KICAgICAgICA8dGhlbWVrZXk+cG9seWdvbjwvdGhlbWVrZXk+DQogICAgICAgIDx0aGVt
ZWtleT5saW5lPC90aGVtZWtleT4NCiAgICAgIDwvdGhlbWU+DQogICAgICA8dGhlbWU+DQogICAg
ICAgIDx0aGVtZWt0Pk5vbmU8L3RoZW1la3Q+DQogICAgICAgIDx0aGVtZWtleT5TdGF0ZSBvciBl
cXVpdmFsZW50IGVudGl0eTwvdGhlbWVrZXk+DQogICAgICAgIDx0aGVtZWtleT5Qb2x5Z29uPC90
aGVtZWtleT4NCiAgICAgIDwvdGhlbWU+DQogICAgICA8cGxhY2U+DQogICAgICAgIDxwbGFjZWt0
PklOQ0lUUy4zOC0yMDB4IChSMjAwNCksSU5DSVRTLjMxLTIwMHggKFIyMDA3KSxJTkNJVFMuNDU0
LTIwMHgsSU5DSVRTIDQ1NS0yMDB4LElOQ0lUUyA0NDYtMjAwODwvcGxhY2VrdD4NCiAgICAgICAg
PHBsYWNla2V5PlVuaXRlZCBTdGF0ZXMgb2YgQW1lcmljYTwvcGxhY2VrZXk+DQogICAgICAgIDxw
bGFjZWtleT5VLlMuPC9wbGFjZWtleT4NCiAgICAgICAgPHBsYWNla2V5PlUuUy5BPC9wbGFjZWtl
eT4NCiAgICAgIDwvcGxhY2U+DQogICAgICA8c3RyYXR1bT4NCiAgICAgICAgPHN0cmF0a2V5Pmdv
dW5kPC9zdHJhdGtleT4NCiAgICAgIDwvc3RyYXR1bT4NCiAgICAgIDx0ZW1wb3JhbD4NCiAgICAg
ICAgPHRlbXBrZXk+MjAxMDwvdGVtcGtleT4NCiAgICAgICAgPHRlbXBrZXk+MjAxMTwvdGVtcGtl
eT4NCiAgICAgICAgPHRlbXBrZXk+MjAxMjwvdGVtcGtleT4NCiAgICAgIDwvdGVtcG9yYWw+DQog
ICAgPC9rZXl3b3Jkcz4NCiAgICA8YWNjY29uc3Q+Tm9uZTwvYWNjY29uc3Q+DQogICAgPHVzZWNv
bnN0Pg0KVGhlIFRJR0VSL0xpbmUgU2hhcGVmaWxlIHByb2R1Y3RzIGFyZSBub3QgY29weXJpZ2h0
ZWQgaG93ZXZlciBUSUdFUi9MaW5lIGFuZCBDZW5zdXMgVElHRVIgYXJlIHJlZ2lzdGVyZWQgdHJh
ZGVtYXJrcyBvZiB0aGUgVS5TLiBDZW5zdXMgQnVyZWF1LiAgVGhlc2UgcHJvZHVjdHMgYXJlIGZy
ZWUgdG8gdXNlIGluIGEgcHJvZHVjdCBvciBwdWJsaWNhdGlvbiwgaG93ZXZlciBhY2tub3dsZWRn
ZW1lbnQgbXVzdCBiZSBnaXZlbiB0byB0aGUgVS5TLiBDZW5zdXMgQnVyZWF1IGFzIHRoZSBzb3Vy
Y2UuDQpUaGUgYm91bmRhcnkgaW5mb3JtYXRpb24gaW4gdGhlIFRJR0VSL0xpbmUgU2hhcGVmaWxl
cyBhcmUgZm9yIHN0YXRpc3RpY2FsIGRhdGEgY29sbGVjdGlvbiBhbmQgdGFidWxhdGlvbiBwdXJw
b3NlcyBvbmx5OyB0aGVpciBkZXBpY3Rpb24gYW5kIGRlc2lnbmF0aW9uIGZvciBzdGF0aXN0aWNh
bCBwdXJwb3NlcyBkb2VzIG5vdCBjb25zdGl0dXRlIGEgZGV0ZXJtaW5hdGlvbiBvZiBqdXJpc2Rp
Y3Rpb25hbCBhdXRob3JpdHkgb3IgcmlnaHRzIG9mIG93bmVyc2hpcCBvciBlbnRpdGxlbWVudCBh
bmQgdGhleSBhcmUgbm90IGxlZ2FsIGxhbmQgZGVzY3JpcHRpb25zLkNvb3JkaW5hdGVzIGluIHRo
ZSBUSUdFUi9MaW5lIHNoYXBlZmlsZXMgaGF2ZSBzaXggaW1wbGllZCBkZWNpbWFsIHBsYWNlcywg
YnV0IHRoZSBwb3NpdGlvbmFsIGFjY3VyYWN5IG9mIHRoZXNlIGNvb3JkaW5hdGVzIGlzIG5vdCBh
cyBncmVhdCBhcyB0aGUgc2l4IGRlY2ltYWwgcGxhY2VzIHN1Z2dlc3QuDQo8L3VzZWNvbnN0Pg0K
ICAgIDxwdGNvbnRhYz4NCiAgICAgIDxjbnRpbmZvPg0KICAgICAgICA8Y250b3JncD4NCiAgICAg
ICAgICA8Y250b3JnPlJlc2VhcmNoIGFuZCBJbm5vdmF0aXZlIFRlY2hub2xvZ3kgQWRtaW5pc3Ry
YXRpb24ncyBCdXJlYXUgb2YgVHJhbnNwb3J0YXRpb24gU3RhdGlzdGljcyAoUklUQS9CVFMpPC9j
bnRvcmc+DQogICAgICAgICAgPGNudHBlcj5PZmZpY2Ugb2YgR2Vvc3BhdGlhbCBJbmZvcm1hdGlv
biBTeXN0ZW1zPC9jbnRwZXI+DQogICAgICAgIDwvY250b3JncD4NCiAgICAgICAgPGNudGFkZHI+
DQogICAgICAgICAgPGFkZHJ0eXBlPm1haWxpbmcgYW5kIHBoeXNpY2FsIGFkZHJlc3M8L2FkZHJ0
eXBlPg0KICAgICAgICAgIDxhZGRyZXNzPjEyMDAgTmV3IEplcnNleSBBdmUsIFNFPC9hZGRyZXNz
Pg0KICAgICAgICAgIDxjaXR5Pldhc2hpbmd0b248L2NpdHk+DQogICAgICAgICAgPHN0YXRlPkRD
PC9zdGF0ZT4NCiAgICAgICAgICA8cG9zdGFsPjIwNTkwPC9wb3N0YWw+DQogICAgICAgICAgPGNv
dW50cnk+VVNBPC9jb3VudHJ5Pg0KICAgICAgICA8L2NudGFkZHI+DQogICAgICAgIDxjbnR2b2lj
ZT4yMDItMzY2LURBVEE8L2NudHZvaWNlPg0KICAgICAgICA8Y250ZmF4PjIwMi0zNjYtMzY0MDwv
Y250ZmF4Pg0KICAgICAgICA8Y250ZW1haWw+YW5zd2Vyc0BidHMuZ292PC9jbnRlbWFpbD4NCiAg
ICAgIDwvY250aW5mbz4NCiAgICA8L3B0Y29udGFjPg0KICAgIDxjcm9zc3JlZj4NCiAgICAgIDxj
aXRlaW5mbz4NCiAgICAgICAgPG9ubGluaz5odHRwOi8vd3d3LmJ0cy5nb3YvcHJvZ3JhbXMvZ2Vv
Z3JhcGhpY19pbmZvcm1hdGlvbl9zZXJ2aWNlcy88L29ubGluaz4NCiAgICAgICAgPGx3b3JrY2l0
Pg0KICAgICAgICAgIDxjaXRlaW5mbz4NCiAgICAgICAgICAgIDxvbmxpbms+aHR0cDovL3d3dy5i
dHMuZ292L3Byb2dyYW1zL2dlb2dyYXBoaWNfaW5mb3JtYXRpb25fc2VydmljZXMvPC9vbmxpbms+
DQogICAgICAgICAgPC9jaXRlaW5mbz4NCiAgICAgICAgPC9sd29ya2NpdD4NCiAgICAgIDwvY2l0
ZWluZm8+DQogICAgPC9jcm9zc3JlZj4NCiAgPC9pZGluZm8+DQogIDxkYXRhcXVhbD4NCiAgICA8
YXR0cmFjYz4NCiAgICAgIDxhdHRyYWNjcj5BY2N1cmF0ZSBhZ2FpbnN0IEZlZGVyYWwgSW5mb3Jt
YXRpb24gUHJvY2Vzc2luZyBTdGFuZGFyZHMgKEZJUFMpLCBGSVBTIFB1YmxpY2F0aW9uIDYtNCwg
YW5kIEZJUFMtNTUgYXQgdGhlIDEwMCUgbGV2ZWwgZm9yIHRoZSBjb2RlcyBhbmQgYmFzZSBuYW1l
cy4gIFRoZSByZW1haW5pbmcgYXR0cmlidXRlIGluZm9ybWF0aW9uIGhhcyBiZWVuIGV4YW1pbmVk
IGJ1dCBoYXMgbm90IGJlZW4gZnVsbHkgdGVzdGVkIGZvciBhY2N1cmFjeS48L2F0dHJhY2NyPg0K
ICAgIDwvYXR0cmFjYz4NCiAgICA8bG9naWM+DQpUaGUgQ2Vuc3VzIEJ1cmVhdSBwZXJmb3JtZWQg
YXV0b21hdGVkIHRlc3RzIHRvIGVuc3VyZSBsb2dpY2FsIGNvbnNpc3RlbmN5IGFuZCBsaW1pdHMg
b2Ygc2hhcGVmaWxlcy4gIFNlZ21lbnRzIG1ha2luZyB1cCB0aGUgb3V0ZXIgYW5kIGlubmVyIGJv
dW5kYXJpZXMgb2YgYSBwb2x5Z29uIHRpZSBlbmQtdG8tZW5kIHRvIGNvbXBsZXRlbHkgZW5jbG9z
ZSB0aGUgYXJlYS4gIEFsbCBwb2x5Z29ucyBhcmUgdGVzdGVkIGZvciBjbG9zdXJlLg0KVGhlIENl
bnN1cyBCdXJlYXUgdXNlcyBpdHMgaW50ZXJuYWxseSBkZXZlbG9wZWQgZ2VvZ3JhcGhpYyB1cGRh
dGUgc3lzdGVtIHRvIGVuaGFuY2UgYW5kIG1vZGlmeSBzcGF0aWFsIGFuZCBhdHRyaWJ1dGUgZGF0
YSBpbiB0aGUgQ2Vuc3VzIE1BRi9USUdFUiBkYXRhYmFzZS4gIFN0YW5kYXJkIGdlb2dyYXBoaWMg
Y29kZXMsIHN1Y2ggYXMgRklQUyBjb2RlcyBmb3Igc3RhdGVzLCBjb3VudGllcywgbXVuaWNpcGFs
aXRpZXMsIGNvdW50eSBzdWJkaXZpc2lvbnMsIHBsYWNlcywgQW1lcmljYW4gSW5kaWFuL0FsYXNr
YSBOYXRpdmUvTmF0aXZlIEhhd2FpaWFuIGFyZWFzLCBhbmQgY29uZ3Jlc3Npb25hbCBkaXN0cmlj
dHMgYXJlIHVzZWQgd2hlbiBlbmNvZGluZyBzcGF0aWFsIGVudGl0aWVzLiAgVGhlIENlbnN1cyBC
dXJlYXUgcGVyZm9ybWVkIHNwYXRpYWwgZGF0YSB0ZXN0cyBmb3IgbG9naWNhbCBjb25zaXN0ZW5j
eSBvZiB0aGUgY29kZXMgZHVyaW5nIHRoZSBjb21waWxhdGlvbiBvZiB0aGUgb3JpZ2luYWwgQ2Vu
c3VzIE1BRi9USUdFUiBkYXRhYmFzZSBmaWxlcy4gIE1vc3Qgb2YgdGhlIGNvZGVzIGZvciBnZW9n
cmFwaGljIGVudGl0aWVzIGV4Y2VwdCBzdGF0ZXMsIGNvdW50aWVzLCB1cmJhbiBhcmVhcywgQ29y
ZSBCYXNlZCBTdGF0aXN0aWNhbCBBcmVhcyAoQ0JTQXMpLCBBbWVyaWNhbiBJbmRpYW4gQXJlYXMg
KEFJQXMpLCBhbmQgY29uZ3Jlc3Npb25hbCBkaXN0cmljdHMgd2VyZSBwcm92aWRlZCB0byB0aGUg
Q2Vuc3VzIEJ1cmVhdSBieSB0aGUgVVNHUywgdGhlIGFnZW5jeSByZXNwb25zaWJsZSBmb3IgbWFp
bnRhaW5pbmcgRklQUyA1NS4gIEZlYXR1cmUgYXR0cmlidXRlIGluZm9ybWF0aW9uIGhhcyBiZWVu
IGV4YW1pbmVkIGJ1dCBoYXMgbm90IGJlZW4gZnVsbHkgdGVzdGVkIGZvciBjb25zaXN0ZW5jeS4N
CkZvciB0aGUgVElHRVIvTGluZSBTaGFwZWZpbGVzLCB0aGUgUG9pbnQgYW5kIFZlY3RvciBPYmpl
Y3QgQ291bnQgZm9yIHRoZSBHLXBvbHlnb24gU0RUUyBQb2ludCBhbmQgVmVjdG9yIE9iamVjdCBU
eXBlIHJlZmxlY3RzIHRoZSBudW1iZXIgb2YgcmVjb3JkcyBpbiB0aGUgc2hhcGVmaWxlIGF0dHJp
YnV0ZSB0YWJsZS4gIEZvciBtdWx0aS1wb2x5Z29uIGZlYXR1cmVzLCBvbmx5IG9uZSBhdHRyaWJ1
dGUgcmVjb3JkIGV4aXN0cyBmb3IgZWFjaCBtdWx0aS1wb2x5Z29uIHJhdGhlciB0aGFuIG9uZSBh
dHRyaWJ1dGUgcmVjb3JkIHBlciBpbmRpdmlkdWFsIEctcG9seWdvbiBjb21wb25lbnQgb2YgdGhl
IG11bHRpLXBvbHlnb24gZmVhdHVyZS4gIFRJR0VSL0xpbmUgU2hhcGVmaWxlIG11bHRpLXBvbHln
b25zIGFyZSBhbiBleGNlcHRpb24gdG8gdGhlIEctcG9seWdvbiBvYmplY3QgdHlwZSBjbGFzc2lm
aWNhdGlvbi4gIFRoZXJlZm9yZSwgd2hlbiBtdWx0aS1wb2x5Z29ucyBleGlzdCBpbiBhIHNoYXBl
ZmlsZSwgdGhlIG9iamVjdCBjb3VudCB3aWxsIGJlIGxlc3MgdGhhbiB0aGUgYWN0dWFsIG51bWJl
ciBvZiBHLXBvbHlnb25zLg0KPC9sb2dpYz4NCiAgICA8Y29tcGxldGU+RGF0YSBjb21wbGV0ZW5l
c3Mgb2YgdGhlIFRJR0VSL0xpbmUgU2hhcGVmaWxlcyByZWZsZWN0cyB0aGUgY29udGVudHMgb2Yg
dGhlIENlbnN1cyBNQUYvVElHRVIgZGF0YWJhc2UgYXQgdGhlIHRpbWUgdGhlIFRJR0VSL0xpbmUg
U2hhcGVmaWxlcyB3ZXJlIGNyZWF0ZWQuPC9jb21wbGV0ZT4NCiAgICA8bGluZWFnZT4NCiAgICAg
IDxzcmNpbmZvPg0KICAgICAgICA8c3JjY2l0ZT4NCiAgICAgICAgICA8Y2l0ZWluZm8+DQogICAg
ICAgICAgICA8b3JpZ2luPlUuUy4gRGVwYXJ0bWVudCBvZiBDb21tZXJjZSwgVS5TLiBDZW5zdXMg
QnVyZWF1LCBHZW9ncmFwaHkgRGl2aXNpb248L29yaWdpbj4NCiAgICAgICAgICAgIDxwdWJkYXRl
PlVucHVibGlzaGVkIE1hdGVyaWFsPC9wdWJkYXRlPg0KICAgICAgICAgICAgPHRpdGxlPkNlbnN1
cyBNQUYvVElHRVIgZGF0YWJhc2U8L3RpdGxlPg0KICAgICAgICAgICAgPG9ubGluaz5odHRwOi8v
d3d3LmJ0cy5nb3YvcHJvZ3JhbXMvZ2VvZ3JhcGhpY19pbmZvcm1hdGlvbl9zZXJ2aWNlcy88L29u
bGluaz4NCiAgICAgICAgICAgIDxsd29ya2NpdD4NCiAgICAgICAgICAgICAgPGNpdGVpbmZvPg0K
ICAgICAgICAgICAgICAgIDxvbmxpbms+aHR0cDovL3d3dy5idHMuZ292L3Byb2dyYW1zL2dlb2dy
YXBoaWNfaW5mb3JtYXRpb25fc2VydmljZXMvPC9vbmxpbms+DQogICAgICAgICAgICAgIDwvY2l0
ZWluZm8+DQogICAgICAgICAgICA8L2x3b3JrY2l0Pg0KICAgICAgICAgIDwvY2l0ZWluZm8+DQog
ICAgICAgIDwvc3JjY2l0ZT4NCiAgICAgICAgPHR5cGVzcmM+b25saW5lPC90eXBlc3JjPg0KICAg
ICAgICA8c3JjdGltZT4NCiAgICAgICAgICA8dGltZWluZm8+DQogICAgICAgICAgICA8cm5nZGF0
ZXM+DQogICAgICAgICAgICAgIDxiZWdkYXRlPjIwMTAwMTwvYmVnZGF0ZT4NCiAgICAgICAgICAg
ICAgPGVuZGRhdGU+MjAxMDA3PC9lbmRkYXRlPg0KICAgICAgICAgICAgPC9ybmdkYXRlcz4NCiAg
ICAgICAgICA8L3RpbWVpbmZvPg0KICAgICAgICAgIDxzcmNjdXJyPnB1YmxpY2F0aW9uIGRhdGU8
L3NyY2N1cnI+DQogICAgICAgIDwvc3JjdGltZT4NCiAgICAgICAgPHNyY2NpdGVhPk1BRi9USUdF
Ujwvc3JjY2l0ZWE+DQogICAgICAgIDxzcmNjb250cj5UaGUgc2VsZWN0ZWQgZ2VvZ3JhcGhpYyBh
bmQgY2FydG9ncmFwaGljIGluZm9ybWF0aW9uIChsaW5lIHNlZ21lbnRzKSBhcmUgZGVyaXZlZCBm
cm9tIHRoZSBVLlMuIENlbnN1cyBCdXJlYXUncyBNYXN0ZXIgQWRkcmVzcyBGaWxlIFRvcG9sb2dp
Y2FsbHkgSW50ZWdyYXRlZCBHZW9ncmFwaGljIEVuY29kaW5nIGFuZCBSZWZlcmVuY2luZyAoTUFG
L1RJR0VSKSBkYXRhYmFzZS48L3NyY2NvbnRyPg0KICAgICAgPC9zcmNpbmZvPg0KICAgICAgPHBy
b2NzdGVwPg0KICAgICAgICA8cHJvY2Rlc2M+VElHRVIvTGluZSBTaGFwZWZpbGVzIGFyZSBleHRy
YWN0ZWQgZnJvbSB0aGUgQ2Vuc3VzIE1BRi9USUdFUiBkYXRhYmFzZSBieSBuYXRpb24sIHN0YXRl
LCBjb3VudHksIGFuZCBlbnRpdHkuICBDZW5zdXMgTUFGL1RJR0VSIGRhdGEgZm9yIGFsbCBvZiB0
aGUgYWZvcmVtZW50aW9uZWQgZ2VvZ3JhcGhpYyBlbnRpdGllcyBhcmUgdGhlbiBkaXN0cmlidXRl
ZCBhbW9uZyB0aGUgc2hhcGVmaWxlcyBlYWNoIGNvbnRhaW5pbmcgYXR0cmlidXRlcyBmb3IgbGlu
ZSwgcG9seWdvbiwgb3IgbGFuZG1hcmsgZ2VvZ3JhcGhpYyBkYXRhLjwvcHJvY2Rlc2M+DQogICAg
ICAgIDxzcmN1c2VkPkNlbnN1cyBNQUYvVElHRVI8L3NyY3VzZWQ+DQogICAgICAgIDxwcm9jZGF0
ZT4yMDEwPC9wcm9jZGF0ZT4NCiAgICAgIDwvcHJvY3N0ZXA+DQogICAgPC9saW5lYWdlPg0KICA8
L2RhdGFxdWFsPg0KICA8c3Bkb2luZm8+DQogICAgPGluZHNwcmVmPkZlZGVyYWwgSW5mb3JtYXRp
b24gUHJvY2Vzc2luZyBTdGFuZGFyZHMgKEZJUFMpLCBBTlNJLCBhbmQgZmVhdHVyZSBuYW1lcy48
L2luZHNwcmVmPg0KICA8L3NwZG9pbmZvPg0KICA8ZWFpbmZvPg0KICAgIDxkZXRhaWxlZCBOYW1l
PSJjb3VudHkiPg0KICAgICAgPGVudHR5cD4NCiAgICAgICAgPGVudHR5cGwgU3luYz0iVFJVRSI+
Y291bnR5PC9lbnR0eXBsPg0KICAgICAgICA8ZW50dHlwZD5FU1JJIHNoYXBlZmlsZSBvZiB0aGUg
VW5pdGVkIFN0YXRlcyBjb3VudGllczwvZW50dHlwZD4NCiAgICAgICAgPGVudHR5cGRzPkVTUkkg
YW5kIFJJVEEvQlRTPC9lbnR0eXBkcz4NCiAgICAgICAgPGVudHR5cHQgU3luYz0iVFJVRSI+RmVh
dHVyZSBDbGFzczwvZW50dHlwdD4NCiAgICAgICAgPGVudHR5cGMgU3luYz0iVFJVRSI+MzIzNDwv
ZW50dHlwYz4NCiAgICAgIDwvZW50dHlwPg0KICAgICAgPGF0dHI+DQogICAgICAgIDxhdHRybGFi
bD5GSUQ8L2F0dHJsYWJsPg0KICAgICAgICA8YXR0cmRlZj5JbnRlcm5hbCBmZWF0dXJlIG51bWJl
ci48L2F0dHJkZWY+DQogICAgICAgIDxhdHRyZGVmcz5FU1JJPC9hdHRyZGVmcz4NCiAgICAgICAg
PGF0dHJkb212Pg0KICAgICAgICAgIDx1ZG9tPlNlcXVlbnRpYWwgdW5pcXVlIHdob2xlIG51bWJl
cnMgdGhhdCBhcmUgYXV0b21hdGljYWxseSBnZW5lcmF0ZWQuPC91ZG9tPg0KICAgICAgICA8L2F0
dHJkb212Pg0KICAgICAgICA8YXR0YWxpYXMgU3luYz0iVFJVRSI+RklEPC9hdHRhbGlhcz4NCiAg
ICAgICAgPGF0dHJ0eXBlIFN5bmM9IlRSVUUiPk9JRDwvYXR0cnR5cGU+DQogICAgICAgIDxhdHR3
aWR0aCBTeW5jPSJUUlVFIj40PC9hdHR3aWR0aD4NCiAgICAgICAgPGF0cHJlY2lzIFN5bmM9IlRS
VUUiPjA8L2F0cHJlY2lzPg0KICAgICAgICA8YXR0c2NhbGUgU3luYz0iVFJVRSI+MDwvYXR0c2Nh
bGU+DQogICAgICA8L2F0dHI+DQogICAgICA8YXR0cj4NCiAgICAgICAgPGF0dHJsYWJsPlNoYXBl
PC9hdHRybGFibD4NCiAgICAgICAgPGF0dHJkZWY+RmVhdHVyZSBnZW9tZXRyeS48L2F0dHJkZWY+
DQogICAgICAgIDxhdHRyZGVmcz5FU1JJPC9hdHRyZGVmcz4NCiAgICAgICAgPGF0dHJkb212Pg0K
ICAgICAgICAgIDxlZG9tPg0KICAgICAgICAgICAgPGVkb212PiJwb2x5Z29uIjwvZWRvbXY+DQog
ICAgICAgICAgICA8ZWRvbXZkPkEgInBvbHlnb24iIGlzIGFuIGFyZWEgZmVhdHVyZSBjb21wcmlz
ZWQgb2YgcG9pbnRzIGFuZCBsaW5lIHNlZ21lbnRzLjwvZWRvbXZkPg0KICAgICAgICAgICAgPGVk
b212ZHM+QXNzaWduZWQ8L2Vkb212ZHM+DQogICAgICAgICAgPC9lZG9tPg0KICAgICAgICA8L2F0
dHJkb212Pg0KICAgICAgICA8YXR0cmRvbXY+DQogICAgICAgICAgPHVkb20+Q29vcmRpbmF0ZXMg
ZGVmaW5pbmcgdGhlIGZlYXR1cmVzLjwvdWRvbT4NCiAgICAgICAgPC9hdHRyZG9tdj4NCiAgICAg
ICAgPGF0dGFsaWFzIFN5bmM9IlRSVUUiPlNoYXBlPC9hdHRhbGlhcz4NCiAgICAgICAgPGF0dHJ0
eXBlIFN5bmM9IlRSVUUiPkdlb21ldHJ5PC9hdHRydHlwZT4NCiAgICAgICAgPGF0dHdpZHRoIFN5
bmM9IlRSVUUiPjA8L2F0dHdpZHRoPg0KICAgICAgICA8YXRwcmVjaXMgU3luYz0iVFJVRSI+MDwv
YXRwcmVjaXM+DQogICAgICAgIDxhdHRzY2FsZSBTeW5jPSJUUlVFIj4wPC9hdHRzY2FsZT4NCiAg
ICAgIDwvYXR0cj4NCiAgICAgIDxhdHRyPg0KICAgICAgICA8YXR0cmxhYmw+U1RGSVBTPC9hdHRy
bGFibD4NCiAgICAgICAgPGF0dHJkZWY+U3RhdGUgRklQUyBjb2RlPC9hdHRyZGVmPg0KICAgICAg
ICA8YXR0cmRlZnM+QnVyZWF1IG9mIHRoZSBDZW5zdXMgKEJPQyk8L2F0dHJkZWZzPg0KICAgICAg
ICA8YXR0cmRvbXY+DQogICAgICAgICAgPGNvZGVzZXRkPg0KICAgICAgICAgICAgPGNvZGVzZXRu
PkZlZGVyYWwgSW5mb3JtYXRpb24gUHJvY2Vzc2luZyBTdGFuZGFyZCwgUHVibGljYXRpb24gNi00
PC9jb2Rlc2V0bj4NCiAgICAgICAgICAgIDxjb2Rlc2V0cz5OYXRpb25hbCBJbnN0aXR1dGUgZm9y
IFN0YW5kYXJkcyBhbmQgVGVjaG5vbG9neTwvY29kZXNldHM+DQogICAgICAgICAgPC9jb2Rlc2V0
ZD4NCiAgICAgICAgPC9hdHRyZG9tdj4NCiAgICAgICAgPGF0dGFsaWFzIFN5bmM9IlRSVUUiPlNU
RklQUzwvYXR0YWxpYXM+DQogICAgICAgIDxhdHRydHlwZSBTeW5jPSJUUlVFIj5TdHJpbmc8L2F0
dHJ0eXBlPg0KICAgICAgICA8YXR0d2lkdGggU3luYz0iVFJVRSI+MjwvYXR0d2lkdGg+DQogICAg
ICAgIDxhdHByZWNpcyBTeW5jPSJUUlVFIj4wPC9hdHByZWNpcz4NCiAgICAgICAgPGF0dHNjYWxl
IFN5bmM9IlRSVUUiPjA8L2F0dHNjYWxlPg0KICAgICAgPC9hdHRyPg0KICAgICAgPGF0dHI+DQog
ICAgICAgIDxhdHRybGFibD5DVEZJUFM8L2F0dHJsYWJsPg0KICAgICAgICA8YXR0cmRlZj5Db3Vu
dHkgRklQUyBjb2RlPC9hdHRyZGVmPg0KICAgICAgICA8YXR0cmRlZnM+QnVyZWF1IG9mIHRoZSBD
ZW5zdXMgKEJPQyk8L2F0dHJkZWZzPg0KICAgICAgICA8YXR0cmRvbXY+DQogICAgICAgICAgPGNv
ZGVzZXRkPg0KICAgICAgICAgICAgPGNvZGVzZXRuPkZlZGVyYWwgSW5mb3JtYXRpb24gUHJvY2Vz
c2luZyBTdGFuZGFyZCwgUHVibGljYXRpb24gNi00PC9jb2Rlc2V0bj4NCiAgICAgICAgICAgIDxj
b2Rlc2V0cz5OYXRpb25hbCBJbnN0aXR1dGUgZm9yIFN0YW5kYXJkcyBhbmQgVGVjaG5vbG9neTwv
Y29kZXNldHM+DQogICAgICAgICAgPC9jb2Rlc2V0ZD4NCiAgICAgICAgPC9hdHRyZG9tdj4NCiAg
ICAgICAgPGF0dGFsaWFzIFN5bmM9IlRSVUUiPkNURklQUzwvYXR0YWxpYXM+DQogICAgICAgIDxh
dHRydHlwZSBTeW5jPSJUUlVFIj5TdHJpbmc8L2F0dHJ0eXBlPg0KICAgICAgICA8YXR0d2lkdGgg
U3luYz0iVFJVRSI+NTwvYXR0d2lkdGg+DQogICAgICAgIDxhdHByZWNpcyBTeW5jPSJUUlVFIj4w
PC9hdHByZWNpcz4NCiAgICAgICAgPGF0dHNjYWxlIFN5bmM9IlRSVUUiPjA8L2F0dHNjYWxlPg0K
ICAgICAgPC9hdHRyPg0KICAgICAgPGF0dHI+DQogICAgICAgIDxhdHRybGFibD5TVEFURTwvYXR0
cmxhYmw+DQogICAgICAgIDxhdHRyZGVmPlN0YXRlIG5hbWU8L2F0dHJkZWY+DQogICAgICAgIDxh
dHRyZGVmcz5CdXJlYXUgb2YgdGhlIENlbnN1cyAoQk9DKTwvYXR0cmRlZnM+DQogICAgICAgIDxh
dHRyZG9tdj4NCiAgICAgICAgICA8Y29kZXNldGQ+DQogICAgICAgICAgICA8Y29kZXNldG4+T2Zm
aWNhbCBMaXN0IG9mIFN0YXRlIE5hbWVzPC9jb2Rlc2V0bj4NCiAgICAgICAgICAgIDxjb2Rlc2V0
cz5CdXJlYXUgb2YgdGhlIENlbnN1cyAoQk9DKTwvY29kZXNldHM+DQogICAgICAgICAgPC9jb2Rl
c2V0ZD4NCiAgICAgICAgPC9hdHRyZG9tdj4NCiAgICAgICAgPGF0dGFsaWFzIFN5bmM9IlRSVUUi
PlNUQVRFPC9hdHRhbGlhcz4NCiAgICAgICAgPGF0dHJ0eXBlIFN5bmM9IlRSVUUiPlN0cmluZzwv
YXR0cnR5cGU+DQogICAgICAgIDxhdHR3aWR0aCBTeW5jPSJUUlVFIj42NjwvYXR0d2lkdGg+DQog
ICAgICAgIDxhdHByZWNpcyBTeW5jPSJUUlVFIj4wPC9hdHByZWNpcz4NCiAgICAgICAgPGF0dHNj
YWxlIFN5bmM9IlRSVUUiPjA8L2F0dHNjYWxlPg0KICAgICAgPC9hdHRyPg0KICAgICAgPGF0dHI+
DQogICAgICAgIDxhdHRybGFibD5DT1VOVFk8L2F0dHJsYWJsPg0KICAgICAgICA8YXR0cmRlZj5D
b3VudHkgbmFtZTwvYXR0cmRlZj4NCiAgICAgICAgPGF0dHJkZWZzPkJ1cmVhdSBvZiB0aGUgQ2Vu
c3VzIChCT0MpPC9hdHRyZGVmcz4NCiAgICAgICAgPGF0dHJkb212Pg0KICAgICAgICAgIDxjb2Rl
c2V0ZD4NCiAgICAgICAgICAgIDxjb2Rlc2V0bj5PZmZpY2lhbCBMaXN0IG9mIFUuUy4gQ291bnR5
IE5hbWVzPC9jb2Rlc2V0bj4NCiAgICAgICAgICAgIDxjb2Rlc2V0cz5CdXJlYXUgb2YgdGhlIENl
bnN1cyAoQk9DKTwvY29kZXNldHM+DQogICAgICAgICAgPC9jb2Rlc2V0ZD4NCiAgICAgICAgPC9h
dHRyZG9tdj4NCiAgICAgICAgPGF0dGFsaWFzIFN5bmM9IlRSVUUiPkNPVU5UWTwvYXR0YWxpYXM+
DQogICAgICAgIDxhdHRydHlwZSBTeW5jPSJUUlVFIj5TdHJpbmc8L2F0dHJ0eXBlPg0KICAgICAg
ICA8YXR0d2lkdGggU3luYz0iVFJVRSI+NjY8L2F0dHdpZHRoPg0KICAgICAgICA8YXRwcmVjaXMg
U3luYz0iVFJVRSI+MDwvYXRwcmVjaXM+DQogICAgICAgIDxhdHRzY2FsZSBTeW5jPSJUUlVFIj4w
PC9hdHRzY2FsZT4NCiAgICAgIDwvYXR0cj4NCiAgICAgIDxhdHRyPg0KICAgICAgICA8YXR0cmxh
Ymw+VkVSU0lPTjwvYXR0cmxhYmw+DQogICAgICAgIDxhdHRyZGVmPlZlcnNpb24gb2YgdGhlIGRh
dGFiYXNlPC9hdHRyZGVmPg0KICAgICAgICA8YXR0cmRlZnM+UmVzZWFyY2ggYW5kIElubm92YXRp
dmUgVGVjaG5vbG9neSBBZG1pbmlzdHJhdGlvbidzIEJ1cmVhdSBvZiBUcmFuc3BvcnRhdGlvbiBT
dGF0aXN0aWNzIChSSVRBL0JUUyk8L2F0dHJkZWZzPg0KICAgICAgICA8YXR0cmRvbXY+DQogICAg
ICAgICAgPHJkb20+DQogICAgICAgICAgICA8cmRvbW1pbj4wMDwvcmRvbW1pbj4NCiAgICAgICAg
ICAgIDxyZG9tbWF4Pjk5PC9yZG9tbWF4Pg0KICAgICAgICAgIDwvcmRvbT4NCiAgICAgICAgPC9h
dHRyZG9tdj4NCiAgICAgICAgPGF0dGFsaWFzIFN5bmM9IlRSVUUiPlZFUlNJT048L2F0dGFsaWFz
Pg0KICAgICAgICA8YXR0cnR5cGUgU3luYz0iVFJVRSI+U3RyaW5nPC9hdHRydHlwZT4NCiAgICAg
ICAgPGF0dHdpZHRoIFN5bmM9IlRSVUUiPjI8L2F0dHdpZHRoPg0KICAgICAgICA8YXRwcmVjaXMg
U3luYz0iVFJVRSI+MDwvYXRwcmVjaXM+DQogICAgICAgIDxhdHRzY2FsZSBTeW5jPSJUUlVFIj4w
PC9hdHRzY2FsZT4NCiAgICAgIDwvYXR0cj4NCiAgICA8L2RldGFpbGVkPg0KICA8L2VhaW5mbz4N
CiAgPGRpc3RpbmZvPg0KICAgIDxkaXN0cmliPg0KICAgICAgPGNudGluZm8+DQogICAgICAgIDxj
bnRvcmdwPg0KICAgICAgICAgIDxjbnRvcmc+UmVzZWFyY2ggYW5kIElubm92YXRpdmUgVGVjaG5v
bG9neSBBZG1pbmlzdHJhdGlvbidzIEJ1cmVhdSBvZiBUcmFuc3BvcnRhdGlvbiBTdGF0aXN0aWNz
IChSSVRBL0JUUyk8L2NudG9yZz4NCiAgICAgICAgICA8Y250cGVyPk9mZmljZSBvZiBHZW9zcGF0
aWFsIEluZm9ybWF0aW9uIFN5c3RlbXM8L2NudHBlcj4NCiAgICAgICAgPC9jbnRvcmdwPg0KICAg
ICAgICA8Y250YWRkcj4NCiAgICAgICAgICA8YWRkcnR5cGU+bWFpbGluZyBhZGRyZXNzPC9hZGRy
dHlwZT4NCiAgICAgICAgICA8YWRkcmVzcz4xMjAwIE5ldyBKZXJzZXkgQXZlbnVlLCBTRTwvYWRk
cmVzcz4NCiAgICAgICAgICA8Y2l0eT5XYXNoaW5ndG9uPC9jaXR5Pg0KICAgICAgICAgIDxzdGF0
ZT5EQzwvc3RhdGU+DQogICAgICAgICAgPHBvc3RhbD4yMDU5MDwvcG9zdGFsPg0KICAgICAgICAg
IDxjb3VudHJ5PlVTQTwvY291bnRyeT4NCiAgICAgICAgPC9jbnRhZGRyPg0KICAgICAgICA8Y250
dm9pY2U+MjAyLTM2Ni1EQVRBPC9jbnR2b2ljZT4NCiAgICAgICAgPGNudGZheD4yMDItMzY2LTM2
NDA8L2NudGZheD4NCiAgICAgICAgPGNudGVtYWlsPmFuc3dlcnNAYnRzLmdvdjwvY250ZW1haWw+
DQogICAgICA8L2NudGluZm8+DQogICAgPC9kaXN0cmliPg0KICAgIDxyZXNkZXNjPk5hdGlvbmFs
IFRyYW5zcG9ydGF0aW9uIEF0bGFzIERhdGFiYXNlcyAoTlRBRCkgMjAxMjwvcmVzZGVzYz4NCiAg
ICA8ZGlzdGxpYWI+Tm8gd2FycmFudHksIGV4cHJlc3NlZCBvciBpbXBsaWVkIGlzIG1hZGUgd2l0
aCByZWdhcmQgdG8gdGhlIGFjY3VyYWN5IG9mIHRoZXNlIGRhdGEsIGFuZCBubyBsaWFiaWxpdHkg
aXMgYXNzdW1lZCBieSB0aGUgVS5TLiBHb3Zlcm5tZW50IGluIGdlbmVyYWwgb3IgdGhlIFUuUy4g
Q2Vuc3VzIEJ1cmVhdSBpbiBzcGVjaWZpYyBhcyB0byB0aGUgc3BhdGlhbCBvciBhdHRyaWJ1dGUg
YWNjdXJhY3kgb2YgdGhlIGRhdGEuICBUaGUgYWN0IG9mIGRpc3RyaWJ1dGlvbiBzaGFsbCBub3Qg
Y29uc3RpdHV0ZSBhbnkgc3VjaCB3YXJyYW50eSBhbmQgbm8gcmVzcG9uc2liaWxpdHkgaXMgYXNz
dW1lZCBieSB0aGUgVS5TLiBnb3Zlcm5tZW50IGluIHRoZSB1c2Ugb2YgdGhlc2UgZmlsZXMuICBU
aGUgYm91bmRhcnkgaW5mb3JtYXRpb24gaW4gdGhlIFRJR0VSL0xpbmUgU2hhcGVmaWxlcyBpcyBm
b3Igc3RhdGlzdGljYWwgZGF0YSBjb2xsZWN0aW9uIGFuZCB0YWJ1bGF0aW9uIHB1cnBvc2VzIG9u
bHk7IHRoZWlyIGRlcGljdGlvbiBhbmQgZGVzaWduYXRpb24gZm9yIHN0YXRpc3RpY2FsIHB1cnBv
c2VzIGRvIG5vdCBjb25zdGl0dXRlIGEgZGV0ZXJtaW5hdGlvbiBvZiBqdXJpc2RpY3Rpb25hbCBh
dXRob3JpdHkgb3IgcmlnaHRzIG9mIG93bmVyc2hpcCBvciBlbnRpdGxlbWVudCBhbmQgdGhleSBh
cmUgbm90IGxlZ2FsIGxhbmQgZGVzY3JpcHRpb25zLjwvZGlzdGxpYWI+DQogICAgPHN0ZG9yZGVy
Pg0KICAgICAgPGRpZ2Zvcm0+DQogICAgICAgIDxkaWd0aW5mbz4NCiAgICAgICAgICA8Zm9ybW5h
bWU+RVNSSSBTaGFwZWZpbGU8L2Zvcm1uYW1lPg0KICAgICAgICAgIDxmb3JtdmVyZD4yMDEyPC9m
b3JtdmVyZD4NCiAgICAgICAgICA8ZmlsZWRlYz5QSy1aSVAsIHZlcnNpb24gMS45MyBBIG9yIGhp
Z2hlcjwvZmlsZWRlYz4NCiAgICAgICAgICA8dHJhbnNpemU+MC4wNjg8L3RyYW5zaXplPg0KICAg
ICAgICA8L2RpZ3RpbmZvPg0KICAgICAgICA8ZGlndG9wdD4NCiAgICAgICAgICA8b25saW5vcHQ+
DQogICAgICAgICAgICA8Y29tcHV0ZXI+DQogICAgICAgICAgICAgIDxuZXR3b3JrYT4NCiAgICAg
ICAgICAgICAgICA8bmV0d29ya3I+aHR0cDovL3d3dy5jZW5zdXMuZ292L2dlby93d3cvdGlnZXI8
L25ldHdvcmtyPg0KICAgICAgICAgICAgICA8L25ldHdvcmthPg0KICAgICAgICAgICAgPC9jb21w
dXRlcj4NCiAgICAgICAgICAgIDxhY2NpbnN0cj5UaGUgTlRBRCBEVkQgY2FuIGJlIG9yZGVyZWQg
ZnJvbSB0aGUgb25saW5lIGJvb2tzdG9yZSBhdCB3d3cuYnRzLmdvdi4gIE5UQUQgY2FuIGFsc28g
YmUgZG93bmxvYWRlZCBmcm9tIHRoZSBHZW9ncmFwaGljIEluZm9ybWF0aW9uIFByb2dyYW0gd2Vi
IHNpdCBhdCBodHRwOi8vd3d3LmJ0cy5nb3YvcHJvZ3JhbXMvZ2VvZ3JhcGhpY19pbmZvcm1hdGlv
bl9zZXJ2aWNlcy8uPC9hY2NpbnN0cj4NCiAgICAgICAgICA8L29ubGlub3B0Pg0KICAgICAgICAg
IDxvZmZvcHRuPg0KICAgICAgICAgICAgPG9mZm1lZGlhPkRWRDwvb2ZmbWVkaWE+DQogICAgICAg
ICAgICA8cmVjZm10PklTTyA5NjYwPC9yZWNmbXQ+DQogICAgICAgICAgPC9vZmZvcHRuPg0KICAg
ICAgICA8L2RpZ3RvcHQ+DQogICAgICA8L2RpZ2Zvcm0+DQogICAgICA8ZmVlcz5UaGUgb25saW5l
IGNvcHkgb2YgdGhlIFRJR0VSL0xpbmUgZmlsZXMgbWF5IGJlIGFjY2Vzc2VkIHdpdGhvdXQgY2hh
cmdlLjwvZmVlcz4NCiAgICAgIDxvcmRlcmluZz5DYWxsICgyMDItMzY2LURBVEEpLCBmYXggKDIw
Mi0zNjYtMzY0MCksIG9yIEUtbWFpbCAoYW5zd2Vyc0BidHMuZ292KSBSSVRBL0JUUyB0byByZXF1
ZXN0IHRoZSBOYXRpb25hbCBUcmFuc3BvcnRhdGlvbiBBdGxhcyBEYXRhYmFzZXMgKE5UQUQpIDIw
MTIgRFZELiBUaGUgTlRBRCBEVkQgY2FuIGJlIG9yZGVyZWQgZnJvbSB0aGUgb25saW5lIGJvb2tz
dG9yZSBhdCB3d3cuYnRzLmdvdi4gIEluZGl2aWR1YWwgZGF0YXNldHMgZnJvbSB0aGUgTlRBRCBj
YW4gYWxzbyBiZSBkb3dubG9hZGVkIGZyb20gdGhlIE9mZmljZSBvZiBHZW9zcGF0aWFsIEluZm9y
bWF0aW9uIFN5c3RlbXMgd2Vic2l0ZSBhdCBodHRwOi8vd3d3LmJ0cy5nb3YvcHJvZ3JhbXMvZ2Vv
Z3JhcGhpY19pbmZvcm1hdGlvbl9zZXJ2aWNlcy8uDQoNClRvIG9idGFpbiBtb3JlIGluZm9ybWF0
aW9uIGFib3V0IG9yZGVyaW5nIFRJR0VSL0xpbmUgc2hhcGVmaWxlcyB2aXNpdCBodHRwOi8vd3d3
LmNlbnN1cy5nb3YvZ2VvL3d3dy90aWdlcjwvb3JkZXJpbmc+DQogICAgPC9zdGRvcmRlcj4NCiAg
ICA8dGVjaHByZXE+DQpTb2Z0d2FyZSB0aGF0IGNhbiBwcm9jZXNzIEdJUyBmaWxlcy4NCg0KVGhl
IFRJR0VSL0xpbmUgc2hhcGVmaWxlcyBjb250YWluIGdlb2dyYXBoaWMgZGF0YSBvbmx5IGFuZCBk
byBub3QgaW5jbHVkZSBkaXNwbGF5IG1hcHBpbmcgc29mdHdhcmUgb3Igc3RhdGlzdGljYWwgZGF0
YS4gIEZvciBpbmZvcm1hdGlvbiBvbiBob3cgdG8gdXNlIHRoZSBUSUdFUi9MaW5lIHNoYXBlZmls
ZSBkYXRhIHdpdGggc3BlY2lmaWMgc29mdHdhcmUgcGFja2FnZSB1c2VycyBzaGFsbCBjb250YWN0
IHRoZSBjb21wYW55IHRoYXQgcHJvZHVjZWQgdGhlIHNvZnR3YXJlLg0KPC90ZWNocHJlcT4NCiAg
ICA8YXZhaWxhYmw+DQogICAgICA8dGltZWluZm8+DQogICAgICAgIDxzbmdkYXRlPg0KICAgICAg
ICAgIDxjYWxkYXRlPjIwMTI8L2NhbGRhdGU+DQogICAgICAgIDwvc25nZGF0ZT4NCiAgICAgIDwv
dGltZWluZm8+DQogICAgPC9hdmFpbGFibD4NCiAgPC9kaXN0aW5mbz4NCiAgPG1ldGFpbmZvPg0K
ICAgIDxtZXRjPg0KICAgICAgPGNudGluZm8+DQogICAgICAgIDxjbnRvcmdwPg0KICAgICAgICAg
IDxjbnRvcmc+UmVzZWFyY2ggYW5kIElubm92YXRpdmUgVGVjaG5vbG9neSBBZG1pbmlzdHJhdGlv
bidzIEJ1cmVhdSBvZiBUcmFuc3BvcnRhdGlvbiBTdGF0aXNpdGljcyAoUklUQS9CVFMpPC9jbnRv
cmc+DQogICAgICAgICAgPGNudHBlcj5PZmZpY2Ugb2YgR2Vvc3BhdGlhbCBJbmZvcm1hdGlvbiBT
eXN0ZW1zPC9jbnRwZXI+DQogICAgICAgIDwvY250b3JncD4NCiAgICAgICAgPGNudGFkZHI+DQog
ICAgICAgICAgPGFkZHJ0eXBlPm1haWxpbmcgYWRkcmVzczwvYWRkcnR5cGU+DQogICAgICAgICAg
PGFkZHJlc3M+MTIwMCBOZXcgSmVyc2V5IEF2ZS48L2FkZHJlc3M+DQogICAgICAgICAgPGNpdHk+
V2FzaGluZ3RvbjwvY2l0eT4NCiAgICAgICAgICA8c3RhdGU+REM8L3N0YXRlPg0KICAgICAgICAg
IDxwb3N0YWw+MjA1OTA8L3Bvc3RhbD4NCiAgICAgICAgICA8Y291bnRyeT5VU0E8L2NvdW50cnk+
DQogICAgICAgIDwvY250YWRkcj4NCiAgICAgICAgPGNudHZvaWNlPjIwMi0zNjYtREFUQTwvY250
dm9pY2U+DQogICAgICAgIDxjbnRmYXg+MjAyLTM2Ni0zNjQwPC9jbnRmYXg+DQogICAgICAgIDxj
bnRlbWFpbD5hbnN3ZXJzQGJ0cy5nb3Y8L2NudGVtYWlsPg0KICAgICAgPC9jbnRpbmZvPg0KICAg
IDwvbWV0Yz4NCiAgICA8bWV0ZXh0bnM+DQogICAgICA8b25saW5rPmh0dHA6Ly93d3cuZXNyaS5j
b20vbWV0YWRhdGEvZXNyaXByb2Y4MC5odG1sPC9vbmxpbms+DQogICAgICA8bWV0cHJvZj5FU1JJ
IE1ldGFkYXRhIFByb2ZpbGU8L21ldHByb2Y+DQogICAgPC9tZXRleHRucz4NCiAgICA8bWV0ZXh0
bnM+DQogICAgICA8b25saW5rPmh0dHA6Ly93d3cuZXNyaS5jb20vbWV0YWRhdGEvZXNyaXByb2Y4
MC5odG1sPC9vbmxpbms+DQogICAgICA8bWV0cHJvZj5FU1JJIE1ldGFkYXRhIFByb2ZpbGU8L21l
dHByb2Y+DQogICAgPC9tZXRleHRucz4NCiAgICA8bWV0ZXh0bnM+DQogICAgICA8b25saW5rPmh0
dHA6Ly93d3cuZXNyaS5jb20vbWV0YWRhdGEvZXNyaXByb2Y4MC5odG1sPC9vbmxpbms+DQogICAg
ICA8bWV0cHJvZj5FU1JJIE1ldGFkYXRhIFByb2ZpbGU8L21ldHByb2Y+DQogICAgPC9tZXRleHRu
cz4NCiAgPC9tZXRhaW5mbz4NCiAgPEVzcmk+DQogICAgPE1ldGFJRD57RTYyNjVCODAtRDFBNS00
RDQ0LUI0Q0YtNTI4REM0MTQ2NTc0fTwvTWV0YUlEPg0KICAgIDxDcmVhRGF0ZT4yMDEyMDIxNzwv
Q3JlYURhdGU+DQogICAgPENyZWFUaW1lPjExMDcwMTAwPC9DcmVhVGltZT4NCiAgICA8U3luY09u
Y2U+RkFMU0U8L1N5bmNPbmNlPg0KICAgIDxTeW5jRGF0ZT4yMDEyMDMwNjwvU3luY0RhdGU+DQog
ICAgPFN5bmNUaW1lPjEwMzMzNTAwPC9TeW5jVGltZT4NCiAgICA8TW9kRGF0ZT4yMDEyMDMwNjwv
TW9kRGF0ZT4NCiAgICA8TW9kVGltZT4xMDMzMzUwMDwvTW9kVGltZT4NCiAgPC9Fc3JpPg0KPC9t
ZXRhZGF0YT4=</Data></Enclosure></Binary><mdHrLvName Sync="TRUE">dataset</mdHrLvName><refSysInfo><RefSystem><refSysID><identCode code="4326" Sync="TRUE" value="4326"/><idCodeSpace Sync="TRUE">EPSG</idCodeSpace><idVersion Sync="TRUE">7.4.1</idVersion></refSysID></RefSystem></refSysInfo><mdDateSt Sync="TRUE">20120524</mdDateSt></metadata>
